Workbook

Sheet PAINEL
A1: CONTROLE DE CARREGAMENTO ULTRAPÃO
A3: RESUMO GERAL | D3: ESTATÍSTICAS POR VEÍCULO
A4: Total de Itens Bipados: | B4: =COUNTA(BASE!A:A)-1 -> 844 | D4: Veículo | E4: Itens Carregados
A5: Total de Itens Carregados: | B5: =COUNTIF(BASE!F:F, "CARREGADO") -> 0
A6: Total de Itens Únicos: | B6: =COUNTA(CONFERENCIA!A:A)-1 -> 999
A7: Total de Divergências: | B7: =COUNTA(DIVERGÊNCIAS!A:A)-1 -> 999
A10: ACESSO RÁPIDO ÀS ABAS
A11: BASE | B11: Cadastro de produtos bipados
A12: CONFERENCIA | B12: Conferência sem repetir códigos
A13: EXTRATO | B13: Relação de itens carregados
A14: ROMANEIO POR ITEM | B14: Conferência com romaneio
A15: DIVERGÊNCIAS | B15: Lista de divergências encontradas
A17: INSTRUÇÕES DE USO
A18: 1. Na aba BASE, registre todos os produtos bipados com código de barras, produto, quantidade, data/hora, veículo e status
A19: 2. A aba CONFERENCIA consolida automaticamente os itens sem repetir códigos de barras
A20: 3. A aba EXTRATO mostra apenas os itens com status 'CARREGADO'
A21: 4. Na aba ROMANEIO POR ITEM, insira manualmente a quantidade do romaneio na coluna D para comparar
A22: 5. A aba DIVERGÊNCIAS mostra automaticamente todas as diferenças encontradas

Sheet BASE
A1: Codigo | B1: Descricao | C1: Tipo | D1: Unidade | E1: Ult. Preco | F1: Ult. Compra | G1: Peso Bruto | H1: Peso Liquido | I1: Peso Cubado | J1: Cod. EAN-13 | K1: Cod. DUN-14
A2: 2000 | B2: GRAMPEADOR | D2: CX | J2: 7896886499716
A3: 01.01.0001 | B3: MASSA CONGELADA DE PAO FRANCES RAPIDA - 5KG | C3: ME | D3: PT | E3: 34.52 | F3: 46070 | G3: 5.018 | H3: 5 | I3: 5 | J3: 7898694171204 | K3: 17898694171201
A4: 01.01.0002 | B4: MASSA CONGELADA DE PAO FRANCES MEDIA - 5KG | C4: ME | D4: PT | E4: 34.73 | F4: 46070 | G4: 5 | H4: 5 | I4: 5 | J4: 7898694171211 | K4: 17898694171218
A5: 01.01.0003 | B5: MASSA CONGELADA DE PAO FRANCES RAPIDA 65G - 5KG | C5: ME | D5: PT | E5: 0 | G5: 5 | H5: 5 | I5: 0 | J5: 7898694171365 | K5: 7898694171365
A6: 01.01.0004 | B6: MASSA CONGELADA DE PAO FRANCES MEDIA 65G - 5KG | C6: ME | D6: PT | E6: 0 | G6: 5 | H6: 5 | I6: 0 | J6: 7898694171372 | K6: 7898694171372
A7: 01.01.0005 | B7: MASSA CONGELADA DE PAO FRANCES BENJAMIN - 5KG | C7: ME | D7: PT | E7: 0 | G7: 5 | H7: 5 | I7: 5 | J7: 7898694171228 | K7: 7898694171228
A8: 01.01.0006 | B8: MASSA CONGELADA DE PAO FRANCES RAPIDA - 10KG | C8: ME | D8: PT | E8: 0 | G8: 5 | H8: 5 | I8: 12 | J8: 17898694171201 | K8: 17898694171201
A9: 01.01.0007 | B9: MASSA CONGELADA DE PAO FRANCES RAPIDA - CX 20KG - 4 UN DE 5KG | C9: ME | D9: CX | E9: 0 | G9: 20.55 | H9: 20 | I9: 0 | J9: 37898694171205
A10: 01.01.0008 | B10: MASSA CONGELADA DE PAO FRANCES RAPIDA - 10 KG | C10: ME | D10: PT | E10: 0 | G10: 0 | H10: 0 | I10: 0
A11: 01.01.1001 | B11: MASSA CONGELADA DE PAO FRANCES RAPIDA (KG) | C11: ME | D11: KG | E11: 0 | G11: 10.01 | H11: 10 | I11: 10.01 | J11: 7898694172805 | K11: 7898694172805
A12: 01.01.1002 | B12: MASSA CONGELADA DE PAO FRANCES MEDIA (KG) | C12: ME | D12: KG | E12: 0 | G12: 10.01 | H12: 10 | I12: 10.01 | J12: 7898694173512 | K12: 7898694173512
A13: 01.02.0001 | B13: MASSA CONGELADA DE MINI PAO FRANCES RAPIDA - 5KG | C13: ME | D13: PT | E13: 36.89 | F13: 46027 | G13: 5 | H13: 5 | I13: 5 | J13: 17898694171263 | K13: 17898694171263
A14: 01.02.0002 | B14: MASSA CONGELADA DE MINI PAO FRANCES MEDIA - 5KG | C14: ME | D14: PT | E14: 0 | G14: 5 | H14: 5 | I14: 0 | J14: 7898694171402 | K14: 7898694171402
A15: 01.02.0003 | B15: MASSA CONGELADA DE MINI PAO FRANCES INTEGRAL RAPIDA - 5KG | C15: ME | D15: PT | E15: 24 | F15: 45930 | G15: 5 | H15: 5 | I15: 5 | J15: 17898694171270 | K15: 17898694171270
A16: 01.02.0004 | B16: MASSA CONGELADA DE MINI PAO FRANCES INTEGRAL MEDIA - 5KG | C16: ME | D16: PT | E16: 0 | G16: 5 | H16: 5 | I16: 0 | J16: 7898694171433 | K16: 7898694171433
A17: 01.02.0005 | B17: MASSA CONGELADA DE PAO FRANCES INTEGRAL RAPIDA - 5KG | C17: ME | D17: PT | E17: 38.72 | F17: 46070 | G17: 5 | H17: 5 | I17: 5 | J17: 17898694171232 | K17: 17898694171232
A18: 01.02.0006 | B18: MASSA CONGELADA DE PAO FRANCES INTEGRAL MEDIA - 5KG | C18: ME | D18: PT | E18: 0 | G18: 5 | H18: 5 | I18: 0 | J18: 7898694171242 | K18: 7898694171242
A19: 01.02.0007 | B19: MASSA CONGELADA DE PAO FRANCES COM GRAOS RAPIDA - 5KG | C19: ME | D19: PT | E19: 45.2 | F19: 46069 | G19: 5 | H19: 5 | I19: 5 | J19: 7898694171341
A20: 01.02.0008 | B20: MASSA CONGELADA DE PAO FRANCES COM GRAOS MEDIA - 5KG | C20: ME | D20: PT | E20: 0 | G20: 5 | H20: 5 | I20: 0 | J20: 7898694171464 | K20: 7898694171464
A21: 01.02.0009 | B21: MASSA CONGELADA DE BAGUETE RAPIDA - 5KG | C21: ME | D21: PT | E21: 24.75 | F21: 46065 | G21: 5 | H21: 5 | I21: 5 | J21: 7898694171327 | K21: 7898694171327
A22: 01.02.0010 | B22: MASSA CONGELADA DE BAGUETE MEDIA - 5KG | C22: ME | D22: PT | E22: 0 | G22: 5 | H22: 5 | I22: 0 | J22: 7898694171426 | K22: 7898694171426
A23: 01.02.0011 | B23: MASSA CONGELADA DE MINI BAGUETE RAPIDA - 5KG | C23: ME | D23: PT | E23: 24.75 | F23: 46065 | G23: 5 | H23: 5 | I23: 5 | J23: 7898694171280
A24: 01.02.0012 | B24: MASSA CONGELADA DE MINI BAGUETE MEDIA - 5KG | C24: ME | D24: PT | E24: 0 | G24: 5 | H24: 5 | I24: 0 | J24: 7898694171419 | K24: 7898694171419
A25: 01.02.0013 | B25: MASSA CONGELADA DE BAGUETE INTEGRAL RAPIDA - 5KG | C25: ME | D25: PT | E25: 0 | G25: 5 | H25: 5 | I25: 0 | J25: 7898694171396 | K25: 7898694171396
A26: 01.02.0014 | B26: MASSA CONGELADA DE BAGUETE INTEGRAL MEDIA - 5KG | C26: ME | D26: PT | E26: 0 | G26: 5 | H26: 5 | I26: 0 | J26: 7898694171457 | K26: 7898694171457
A27: 01.02.0015 | B27: MASSA CONGELADA DE MINI BAGUETE INTEGRAL RAPIDA - 5KG | C27: ME | D27: PT | E27: 0 | G27: 5 | H27: 5 | I27: 0 | J27: 7898694171297 | K27: 7898694171297
A28: 01.02.0016 | B28: MASSA CONGELADA DE MINI BAGUETE INTEGRAL MEDIA - 5KG | C28: ME | D28: PT | E28: 0 | G28: 5 | H28: 5 | I28: 0 | J28: 7898694171440 | K28: 7898694171440
A29: 01.02.0017 | B29: MASSA CONGELADA DE PAO FRANCES BOLA RAPIDA - 5KG | C29: ME | D29: PT | E29: 0 | G29: 5 | H29: 5 | I29: 0
A30: 01.02.0018 | B30: MASSA CONGELADA DE BENZINHO BENJAMIN - 4KG | C30: ME | D30: PT | E30: 0 | G30: 4 | H30: 4 | I30: 5
A31: 01.02.0019 | B31: MASSA CONGELADA DE BENZINHO BENJAMIN - 5KG | C31: ME | D31: PT | E31: 0 | G31: 5 | H31: 5 | I31: 0 | J31: 7898694171389 | K31: 7898694171389
A32: 01.02.0020 | B32: MASSA CONGELADA DE PAO FRANCES INTEGRAL BENJAMIN - 5KG | C32: ME | D32: PT | E32: 0 | G32: 5 | H32: 5 | I32: 0 | J32: 7898694171259 | K32: 7898694171259
A33: 01.02.0021 | B33: MASSA CONGELADA DE PAO FRANCES COM GRAOS BENJAMIN - 5KG | C33: ME | D33: PT | E33: 0 | G33: 5 | H33: 5 | I33: 5 | J33: 7898694171341 | K33: 7898694171341
A34: 01.02.0022 | B34: MASSA CONGELADA DE MINI BAGUETE BENJAMIN - 5KG | C34: ME | D34: PT | E34: 0 | G34: 5 | H34: 5 | I34: 0 | J34: 7898694171303 | K34: 7898694171303
A35: 01.02.0023 | B35: MASSA CONGELADA DE MINI BAGUETE INTEGRAL BENJAMIN - 5KG | C35: ME | D35: PT | E35: 0 | G35: 5 | H35: 5 | I35: 0 | J35: 7898694171310 | K35: 7898694171310
A36: 01.02.0024 | B36: MASSA CONGELADA DE MINI BAGUETE COM PARMESAO BENJAMIN - 5KG | C36: ME | D36: PT | E36: 0 | G36: 5 | H36: 5 | I36: 0
A37: 01.02.0025 | B37: MASSA CONGELADA DE PAO FRANCES INTEGRAL RAPIDA - 10KG | C37: ME | D37: CX | E37: 0 | G37: 0 | H37: 10 | I37: 12
A38: 01.02.0026 | B38: MASSA CONGELADA DE PAO FRANCES COM GRAOS RAPIDA - CX 10KG - 2 UN DE 5KG | C38: ME | D38: CX | E38: 0 | G38: 10 | H38: 10 | I38: 0 | J38: 178986941713486 | K38: 78986941713418
A39: 01.02.0027 | B39: MASSA CONGELADA DE MINI PAO FRANCES RAPIDA - CX 10KG - 2 UN DE 5KG | C39: ME | D39: CX | E39: 20.5 | F39: 45338 | G39: 10.36 | H39: 10 | I39: 0
A40: 01.02.0028 | B40: MASSA CONGELADA DE BAGUETE RAPIDA - CX 10KG - 2 UN DE 5KG | C40: ME | D40: CX | E40: 20.5 | F40: 45322 | G40: 10.63 | H40: 10 | I40: 0 | K40: 27898694171321
A41: 01.02.0029 | B41: MASSA CONGELADA DE MINI BAGUETE RAPIDA - CX 10KG - 2 UN DE 5KG | C41: ME | D41: CX | E41: 20.5 | F41: 45322 | G41: 10.63 | H41: 10 | I41: 0 | K41: 47898694171288
A42: 01.02.0030 | B42: MASSA CONGELADA DE PAO FRANCES BOLA RAPIDA - CX - 10 KG | C42: ME | D42: CX | E42: 0 | G42: 0 | H42: 10 | I42: 0
A43: 01.02.1001 | B43: MASSA CONGELADA DE MINI PAO FRANCES RAPIDA (KG) | C43: ME | D43: KG | E43: 0 | G43: 5.01 | H43: 5 | I43: 5.01 | J43: 7898694173529 | K43: 7898694173529
A44: 01.02.1003 | B44: MASSA CONGELADA DE MINI PAO FRANCES INTEGRAL RAPIDA (KG) | C44: ME | D44: KG | E44: 0 | G44: 5.01 | H44: 5 | I44: 5.01 | J44: 7898694173536 | K44: 7898694173536
A45: 01.02.1005 | B45: MASSA CONGELADA DE PAO FRANCES INTEGRAL RAPIDA (KG) | C45: ME | D45: KG | E45: 0 | G45: 10.01 | H45: 10 | I45: 10.01 | J45: 7898694172843 | K45: 7898694172843
A46: 01.02.1007 | B46: MASSA CONGELADA DE PAO FRANCES COM GRAOS RAPIDA (KG) | C46: ME | D46: KG | E46: 0 | G46: 10.01 | H46: 10 | I46: 10.01 | J46: 7898694172850 | K46: 7898694172850
A47: 01.02.1009 | B47: MASSA CONGELADA DE BAGUTE RAPIDA (KG) | C47: ME | D47: KG | E47: 0 | G47: 5.01 | H47: 5 | I47: 5.01 | J47: 7898694173543 | K47: 7898694173543
A48: 01.02.1011 | B48: MASSA CONGELADA DE MINI BAGUETE RAPIDA (KG) | C48: ME | D48: KG | E48: 0 | G48: 5.01 | H48: 5 | I48: 5.01 | J48: 7898694173550 | K48: 7898694173550
A49: 01.03.0001 | B49: MASSA CONGELADA DE PAO DE MILHO BOLEADO - 5KG | C49: ME | D49: PT | E49: 0 | G49: 5 | H49: 5 | I49: 0
A50: 01.03.0002 | B50: MASSA CONGELADA DE PAO DE BATATA BOLEADO - 5KG | C50: ME | D50: PT | E50: 0 | G50: 5 | H50: 5 | I50: 0
A51: 01.03.0003 | B51: MASSA CONGELADA DE PAO DE CEBOLA BOLEADO - 5KG | C51: ME | D51: PT | E51: 0 | G51: 5 | H51: 5 | I51: 0
A52: 01.03.0004 | B52: MASSA CONGELADA DE ROSCA LISA - 5KG | C52: ME | D52: PT | E52: 50.11 | F52: 45910 | G52: 5 | H52: 5 | I52: 5 | K52: 7898694173567
A53: 01.03.0005 | B53: MASSA CONGELADA DE ROSCA TRANCADA PEQUENA - 5KG | C53: ME | D53: PT | E53: 0 | G53: 5 | H53: 5 | I53: 0
A54: 01.03.0006 | B54: MASSA CONGELADA DE ROSCA TRANCADA GRANDE - 5KG | C54: ME | D54: PT | E54: 0 | G54: 5 | H54: 5 | I54: 0
A55: 01.03.0007 | B55: MASSA CONGELADA DE ROSCA CARACOL - 5KG | C55: ME | D55: PT | E55: 0 | G55: 5 | H55: 5 | I55: 0
A56: 01.03.0008 | B56: MASSA CONGELADA DE FORROZINHO COM CREME E COCO - 5KG | C56: ME | D56: PT | E56: 0 | G56: 5 | H56: 5 | I56: 0
A57: 01.03.0009 | B57: MASSA CONGELADA DE FORROZINHO COM CREME COCO E CHOCOLATE - 5KG | C57: ME | D57: PT | E57: 0 | G57: 5 | H57: 5 | I57: 0
A58: 01.03.0010 | B58: MASSA CONGELADA DE PAO FOFINHO - 5KG | C58: ME | D58: PT | E58: 0 | G58: 5 | H58: 5 | I58: 0
A59: 01.03.0011 | B59: MASSA CONGELADA DE PAO CASEIRAO - 5KG | C59: ME | D59: PT | E59: 0 | G59: 5 | H59: 5 | I59: 0
A60: 01.03.0012 | B60: MASSA CONGELADA DE PÃO CASEIRINHO - 5KG | C60: ME | D60: PT | E60: 0 | G60: 5 | H60: 5 | I60: 0
A61: 01.03.0013 | B61: MASSA CONGELADA DE PAO HOT DOG - 5KG | C61: ME | D61: PT | E61: 0 | G61: 5 | H61: 5 | I61: 0
A62: 01.03.0014 | B62: MASSA CONGELADA DE PAO DE HAMBURGUER - 5KG | C62: ME | D62: PT | E62: 0 | G62: 5 | H62: 5 | I62: 0
A63: 01.03.0015 | B63: MASSA CONGELADA DE PAO DA FAZENDA - 5KG | C63: ME | D63: PT | E63: 0 | G63: 5 | H63: 5 | I63: 0
A64: 01.03.0016 | B64: MASSA CONGELADA DE CROISSANT SEMI FOLHADO 370G - 5KG | C64: ME | D64: PT | E64: 0 | G64: 5 | H64: 5 | I64: 0
A65: 01.03.0019 | B65: MASSA CONGELADA DE ROSCA LISA (PAO DE LEITE) - CX 10 KG - 2 UN DE 5KG | C65: ME | D65: CX | E65: 75 | F65: 46065 | G65: 10.63 | H65: 10 | I65: 0 | J65: 27898694170805 | K65: 27898694170805
A66: 01.03.1004 | B66: MASSA CONGELADA DE ROSCA LISA (PAO DE LEITE) (KG) | C66: ME | D66: KG | E66: 0 | G66: 5.01 | H66: 5 | I66: 5.01 | J66: 7898694173567 | K66: 7898694173567
A67: 01.03.1021 | B67: MASSA CONGELADA DE PAO DE RABANADA - 25 KG | C67: ME | D67: KG | E67: 0 | G67: 25.56 | H67: 25 | I67: 25 | J67: 7898694172294 | K67: 7898694172294
A68: 01.04.0001 | B68: MASSA CONGELADA DE PAO DE QUEIJO TRADICIONAL PEQUENO 30G - 7KG | C68: ME | D68: PT | E68: 99.4 | F68: 46049 | G68: 7 | H68: 7 | I68: 7
A69: 01.04.0002 | B69: MASSA CONGELADA DE PAO DE QUEIJO TRADICIONAL GRANDE 90G - 7KG | C69: ME | D69: PT | E69: 122.1 | F69: 46035 | G69: 7 | H69: 7 | I69: 7
A70: 01.04.0003 | B70: MASSA CONGELADA DE PAO DE QUEIJO EMPANADO BENJAMIN DE 15G - 4KG | C70: ME | D70: PT | E70: 0 | G70: 4 | H70: 4 | I70: 4
A71: 01.04.0004 | B71: MASSA CONGELADA DE PAO DE QUEIJO EMPANADO BENJAMIN DE 100G - 4KG | C71: ME | D71: PT | E71: 0 | G71: 4 | H71: 4 | I71: 4
A72: 01.04.0005 | B72: MASSA CONGELADA DE PAO DE QUEIJO RECHEADO COM GOIABADA BENJAMIN DE 100G - 1KG | C72: ME | D72: PT | E72: 24.6 | F72: 46043 | G72: 1 | H72: 1 | I72: 0
A73: 01.04.0006 | B73: MASSA CONGELADA DE PAO DE QUEIJO RECHEADO COM REQUEIJAO BENJAMIN DE 100G - 1KG | C73: ME | D73: PT | E73: 24.3 | F73: 46043 | G73: 1 | H73: 1 | I73: 0
A74: 01.04.0007 | B74: PAO DE QUEIJO TRADICIONAL 30G - CX 10KG | C74: ME | D74: CX | E74: 0 | G74: 10 | H74: 10 | I74: 0
A75: 01.04.0008 | B75: PAO DE QUEIJO EMPANADO 30G - CX 10KG | C75: ME | D75: CX | E75: 170.5 | F75: 46070 | G75: 10 | H75: 10 | I75: 12
A76: 01.04.0009 | B76: PAO DE QUEIJO MULTIGRAOS EMPANADO 30G - CX 10KG | C76: ME | D76: CX | E76: 182.57 | F76: 45903 | G76: 10 | H76: 10 | I76: 12
A77: 01.04.0010 | B77: MASSA CONGELADA DE PAO DE QUEIJO TRADICIONAL CLASSE A 30G - 8 PCT DE 1KG | C77: ME | D77: FR | E77: 0 | G77: 8 | H77: 8 | I77: 8 | J77: 7898966947360 | K77: 7898966947360
A78: 01.04.0011 | B78: MASSA CONGELADA DE PAO DE QUEIJO PREMIUM CLASSE A 30G - 20 PCT DE 400G | C78: ME | D78: FR | E78: 0 | G78: 8 | H78: 8 | I78: 0
A79: 01.04.0012 | B79: MASSA CONGELADA DE PAO DE QUEIJO 15G NATURAL DA TERRA - CX 8KG - 20 UN DE 400G | C79: ME | D79: CX | E79: 11 | F79: 45692 | G79: 8 | H79: 8 | I79: 12 | J79: 7898694171815 | K79: 7898694171815
A80: 01.04.0013 | B80: MASSA CONGELADA DE PAO DE QUEIJO 30G NATURAL DA TERRA - CX 8KG - 20 UN DE 400G | C80: ME | D80: CX | E80: 0 | G80: 8 | H80: 8 | I80: 12 | J80: 7898694171808 | K80: 7898694171808
A81: 01.04.0014 | B81: MASSA CONGELADA DE PAO DE QUEIJO ST MARCHE 30G - CX 8KG - 20 UN DE 400G | C81: ME | D81: CX | E81: 210.6 | F81: 46059 | G81: 8 | H81: 8 | I81: 0 | J81: 7898694172591 | K81: 7898694172591
A82: 01.04.0015 | B82: MASSA CONGELADA DE BISCOITO DE POLVILHO - 5KG | C82: ME | D82: PT | E82: 0 | G82: 5 | H82: 5 | I82: 0
A83: 01.04.0016 | B83: MASSA CONGELADA DE PAO DE QUEIJO 30G NATURAL DA TERRA - CX 10KG - 10 UN DE 1KG | C83: ME | D83: CX | E83: 0 | G83: 10 | H83: 10 | I83: 12 | J83: 7898694171914 | K83: 7898694171914
A84: 01.04.0017 | B84: MASSA CONGELADA DE PAO DE QUEIJO MULTIGRAOS EMPANADO - 80G - 4KG | C84: ME | D84: PT | E84: 0 | G84: 0 | H84: 4 | I84: 0
A85: 01.04.0018 | B85: MASSA CONGELADA DE PAO DE QUEIJO TRADICIONAL 30G - CX 10KG - PCT 1KG | C85: ME | D85: CX | E85: 0 | G85: 0 | H85: 10 | I85: 0
A86: 01.04.0019 | B86: MASSA CONGELADA DE CHIPA QUEIJO CANASTRA 45G - 4KG | C86: ME | D86: PT | E86: 105.64 | F86: 46065 | G86: 2.014 | H86: 4 | I86: 4
A87: 01.04.0020 | B87: MASSA CONGELADA DE BISCOITO PALITO 3 QUEIJOS 45G - 4KG | C87: ME | D87: PT | E87: 110.38 | F87: 46058 | G87: 2.014 | H87: 4 | I87: 4
A88: 01.04.0021 | B88: MASSA CONGELADA DE PÃO DE QUEIJO RECHEADO DE GOIABADA 65G - 2KG | C88: ME | D88: PT | E88: 59.85 | F88: 46069 | G88: 10.63 | H88: 10 | I88: 10
A89: 01.04.0022 | B89: MASSA CONGELADA DE PÃO DE QUEIJO RECHEADO DE REQUEIJÃO 65G - 2KG | C89: ME | D89: PT | E89: 62.63 | F89: 46069 | G89: 10.63 | H89: 10 | I89: 10
A90: 01.04.0023 | B90: MASSA CONGELADA DE PAO DE QUEIJO EMPANADO PREMIUM 35G - 4KG | C90: ME | D90: PT | E90: 0 | G90: 0 | H90: 0 | I90: 0
A91: 01.04.0024 | B91: MASSA CONGELADA DE CHIPA TRADICIONAL 35G - 2KG | C91: ME | D91: PT | E91: 33.78 | F91: 46055 | G91: 2.014 | H91: 2 | I91: 2
A92: 01.04.0025 | B92: MASSA CONGELADA DE CHIPA QUEIJO CANASTRA ST MARCHE 45G - 20 PCTS DE 400G | C92: ME | D92: CX | E92: 243.2 | F92: 46065 | G92: 8.63 | H92: 8 | I92: 10 | J92: 7898694172140 | K92: 7898694172140
A93: 01.04.0026 | B93: MASSA CONGELADA DE BISCOITO PALITO 3 QUEIJOS ST MARCHE 45G - 20 PCTS DE 400G | C93: ME | D93: CX | E93: 243.2 | F93: 46037 | G93: 8 | H93: 8 | I93: 12 | J93: 7898694172157 | K93: 7898694172157
A94: 01.04.0027 | B94: M. CONG. DE PAO DE QUEIJO RECHEADO DE GOIABADA ST MARCHE 65G - 20 PCTS DE 400G | C94: ME | D94: CX | E94: 0 | G94: 0 | H94: 0 | I94: 0
A95: 01.04.0028 | B95: M. CONG. DE PAO DE QUEIJO RECHEADO DE REQUEIJAO ST MARCHE 65G - 20 PCTS DE 400G | C95: ME | D95: CX | E95: 1 | F95: 45692 | G95: 0 | H95: 0 | I95: 0
A96: 01.04.0029 | B96: M. CONG. DE PAO DE QUEIJO CANASTRA CHEIRIN BAO 15G - CX 10KG - 10 UN DE 1KG | C96: ME | D96: CX | E96: 0 | G96: 0 | H96: 0 | I96: 0
A97: 01.04.0030 | B97: M. CONG. DE PAO DE QUEIJO CANASTRA CHEIRIN BAO 80G - CX 10KG - 10 UN DE 1KG | C97: ME | D97: CX | E97: 0 | G97: 0 | H97: 0 | I97: 0
A98: 01.04.0031 | B98: M. CONG. DE PAO DE QUEIJO CHEIRIN BAO 15G - CX 10KG - 10 UN DE 1KG | C98: ME | D98: CX | E98: 210 | F98: 45708 | G98: 10.53 | H98: 10 | I98: 12 | J98: 7898694172515 | K98: 7898694172515
A99: 01.04.0032 | B99: M. CONG. DE PAO DE QUEIJO CHEIRIN BAO 80G - CX 10KG - 10 UN DE 1KG | C99: ME | D99: CX | E99: 0 | G99: 10.53 | H99: 10 | I99: 12 | J99: 7898694172522 | K99: 7898694172522
A100: 01.04.0033 | B100: MASSA CONG. DE PAO DE QUEIJO EMPORIO SANTA MARIA 30G - FR 8KG - 20 UN DE 400G | C100: ME | D100: FR | E100: 0 | G100: 0 | H100: 8 | I100: 0
...

Sheet CONFERENCIA
A1: CÓDIGO DE BARRAS | B1: PRODUTO | C1: QUANTIDADE TOTAL | D1: ÚLTIMA DATA/HORA | E1: VEÍCULO
A2: 7896886499716 | B2: =IF(A2="", "", VLOOKUP(A2, BASE!$A$4:$B$10003, 2, FALSE)) -> #N/A | C2: =IF(A2="", "", SUMIF(BASE!$A$4:$A$10003, A2, BASE!$C$4:$C$10003)) -> 0 | D2: =IF(A2="", "", INDEX(BASE!$D$4:$D$10003, MATCH(A2, BASE!$A$4:$A$10003, 0))) -> #N/A | E2: =IF(A2="", "", INDEX(BASE!$E$4:$E$10003, MATCH(A2, BASE!$A$4:$A$10003, 0))) -> #N/A
A3: 7896886499716 | B3: =IF(A3="", "", VLOOKUP(A3, BASE!$A$4:$B$10003, 2, FALSE)) -> #N/A | C3: =IF(A3="", "", SUMIF(BASE!$A$4:$A$10003, A3, BASE!$C$4:$C$10003)) -> 0 | D3: =IF(A3="", "", INDEX(BASE!$D$4:$D$10003, MATCH(A3, BASE!$A$4:$A$10003, 0))) -> #N/A | E3: =IF(A3="", "", INDEX(BASE!$E$4:$E$10003, MATCH(A3, BASE!$A$4:$A$10003, 0))) -> #N/A
A4: =IFERROR(INDEX(BASE!$A$4:$A$10003, MATCH(0, COUNTIF($A$1:A3, BASE!$A$4:$A$10003&""), 0)), "") | B4: =IF(A4="", "", VLOOKUP(A4, BASE!$A$4:$B$10003, 2, FALSE)) | C4: =IF(A4="", "", SUMIF(BASE!$A$4:$A$10003, A4, BASE!$C$4:$C$10003)) | D4: =IF(A4="", "", INDEX(BASE!$D$4:$D$10003, MATCH(A4, BASE!$A$4:$A$10003, 0))) | E4: =IF(A4="", "", INDEX(BASE!$E$4:$E$10003, MATCH(A4, BASE!$A$4:$A$10003, 0)))
A5: =IFERROR(INDEX(BASE!$A$4:$A$10003, MATCH(0, COUNTIF($A$1:A4, BASE!$A$4:$A$10003&""), 0)), "") | B5: =IF(A5="", "", VLOOKUP(A5, BASE!$A$4:$B$10003, 2, FALSE)) | C5: =IF(A5="", "", SUMIF(BASE!$A$4:$A$10003, A5, BASE!$C$4:$C$10003)) | D5: =IF(A5="", "", INDEX(BASE!$D$4:$D$10003, MATCH(A5, BASE!$A$4:$A$10003, 0))) | E5: =IF(A5="", "", INDEX(BASE!$E$4:$E$10003, MATCH(A5, BASE!$A$4:$A$10003, 0)))
A6: =IFERROR(INDEX(BASE!$A$4:$A$10003, MATCH(0, COUNTIF($A$1:A5, BASE!$A$4:$A$10003&""), 0)), "") | B6: =IF(A6="", "", VLOOKUP(A6, BASE!$A$4:$B$10003, 2, FALSE)) | C6: =IF(A6="", "", SUMIF(BASE!$A$4:$A$10003, A6, BASE!$C$4:$C$10003)) | D6: =IF(A6="", "", INDEX(BASE!$D$4:$D$10003, MATCH(A6, BASE!$A$4:$A$10003, 0))) | E6: =IF(A6="", "", INDEX(BASE!$E$4:$E$10003, MATCH(A6, BASE!$A$4:$A$10003, 0)))
A7: =IFERROR(INDEX(BASE!$A$4:$A$10003, MATCH(0, COUNTIF($A$1:A6, BASE!$A$4:$A$10003&""), 0)), "") | B7: =IF(A7="", "", VLOOKUP(A7, BASE!$A$4:$B$10003, 2, FALSE)) | C7: =IF(A7="", "", SUMIF(BASE!$A$4:$A$10003, A7, BASE!$C$4:$C$10003)) | D7: =IF(A7="", "", INDEX(BASE!$D$4:$D$10003, MATCH(A7, BASE!$A$4:$A$10003, 0))) | E7: =IF(A7="", "", INDEX(BASE!$E$4:$E$10003, MATCH(A7, BASE!$A$4:$A$10003, 0)))
A8: =IFERROR(INDEX(BASE!$A$4:$A$10003, MATCH(0, COUNTIF($A$1:A7, BASE!$A$4:$A$10003&""), 0)), "") | B8: =IF(A8="", "", VLOOKUP(A8, BASE!$A$4:$B$10003, 2, FALSE)) | C8: =IF(A8="", "", SUMIF(BASE!$A$4:$A$10003, A8, BASE!$C$4:$C$10003)) | D8: =IF(A8="", "", INDEX(BASE!$D$4:$D$10003, MATCH(A8, BASE!$A$4:$A$10003, 0))) | E8: =IF(A8="", "", INDEX(BASE!$E$4:$E$10003, MATCH(A8, BASE!$A$4:$A$10003, 0)))
A9: =IFERROR(INDEX(BASE!$A$4:$A$10003, MATCH(0, COUNTIF($A$1:A8, BASE!$A$4:$A$10003&""), 0)), "") | B9: =IF(A9="", "", VLOOKUP(A9, BASE!$A$4:$B$10003, 2, FALSE)) | C9: =IF(A9="", "", SUMIF(BASE!$A$4:$A$10003, A9, BASE!$C$4:$C$10003)) | D9: =IF(A9="", "", INDEX(BASE!$D$4:$D$10003, MATCH(A9, BASE!$A$4:$A$10003, 0))) | E9: =IF(A9="", "", INDEX(BASE!$E$4:$E$10003, MATCH(A9, BASE!$A$4:$A$10003, 0)))
A10: =IFERROR(INDEX(BASE!$A$4:$A$10003, MATCH(0, COUNTIF($A$1:A9, BASE!$A$4:$A$10003&""), 0)), "") | B10: =IF(A10="", "", VLOOKUP(A10, BASE!$A$4:$B$10003, 2, FALSE)) | C10: =IF(A10="", "", SUMIF(BASE!$A$4:$A$10003, A10, BASE!$C$4:$C$10003)) | D10: =IF(A10="", "", INDEX(BASE!$D$4:$D$10003, MATCH(A10, BASE!$A$4:$A$10003, 0))) | E10: =IF(A10="", "", INDEX(BASE!$E$4:$E$10003, MATCH(A10, BASE!$A$4:$A$10003, 0)))
A11: =IFERROR(INDEX(BASE!$A$4:$A$10003, MATCH(0, COUNTIF($A$1:A10, BASE!$A$4:$A$10003&""), 0)), "") | B11: =IF(A11="", "", VLOOKUP(A11, BASE!$A$4:$B$10003, 2, FALSE)) | C11: =IF(A11="", "", SUMIF(BASE!$A$4:$A$10003, A11, BASE!$C$4:$C$10003)) | D11: =IF(A11="", "", INDEX(BASE!$D$4:$D$10003, MATCH(A11, BASE!$A$4:$A$10003, 0))) | E11: =IF(A11="", "", INDEX(BASE!$E$4:$E$10003, MATCH(A11, BASE!$A$4:$A$10003, 0)))
A12: =IFERROR(INDEX(BASE!$A$4:$A$10003, MATCH(0, COUNTIF($A$1:A11, BASE!$A$4:$A$10003&""), 0)), "") | B12: =IF(A12="", "", VLOOKUP(A12, BASE!$A$4:$B$10003, 2, FALSE)) | C12: =IF(A12="", "", SUMIF(BASE!$A$4:$A$10003, A12, BASE!$C$4:$C$10003)) | D12: =IF(A12="", "", INDEX(BASE!$D$4:$D$10003, MATCH(A12, BASE!$A$4:$A$10003, 0))) | E12: =IF(A12="", "", INDEX(BASE!$E$4:$E$10003, MATCH(A12, BASE!$A$4:$A$10003, 0)))
A13: =IFERROR(INDEX(BASE!$A$4:$A$10003, MATCH(0, COUNTIF($A$1:A12, BASE!$A$4:$A$10003&""), 0)), "") | B13: =IF(A13="", "", VLOOKUP(A13, BASE!$A$4:$B$10003, 2, FALSE)) | C13: =IF(A13="", "", SUMIF(BASE!$A$4:$A$10003, A13, BASE!$C$4:$C$10003)) | D13: =IF(A13="", "", INDEX(BASE!$D$4:$D$10003, MATCH(A13, BASE!$A$4:$A$10003, 0))) | E13: =IF(A13="", "", INDEX(BASE!$E$4:$E$10003, MATCH(A13, BASE!$A$4:$A$10003, 0)))
A14: =IFERROR(INDEX(BASE!$A$4:$A$10003, MATCH(0, COUNTIF($A$1:A13, BASE!$A$4:$A$10003&""), 0)), "") | B14: =IF(A14="", "", VLOOKUP(A14, BASE!$A$4:$B$10003, 2, FALSE)) | C14: =IF(A14="", "", SUMIF(BASE!$A$4:$A$10003, A14, BASE!$C$4:$C$10003)) | D14: =IF(A14="", "", INDEX(BASE!$D$4:$D$10003, MATCH(A14, BASE!$A$4:$A$10003, 0))) | E14: =IF(A14="", "", INDEX(BASE!$E$4:$E$10003, MATCH(A14, BASE!$A$4:$A$10003, 0)))
A15: =IFERROR(INDEX(BASE!$A$4:$A$10003, MATCH(0, COUNTIF($A$1:A14, BASE!$A$4:$A$10003&""), 0)), "") | B15: =IF(A15="", "", VLOOKUP(A15, BASE!$A$4:$B$10003, 2, FALSE)) | C15: =IF(A15="", "", SUMIF(BASE!$A$4:$A$10003, A15, BASE!$C$4:$C$10003)) | D15: =IF(A15="", "", INDEX(BASE!$D$4:$D$10003, MATCH(A15, BASE!$A$4:$A$10003, 0))) | E15: =IF(A15="", "", INDEX(BASE!$E$4:$E$10003, MATCH(A15, BASE!$A$4:$A$10003, 0)))
... A1000: =IFERROR(INDEX(BASE!$A$4:$A$10003, MATCH(0, COUNTIF($A$1:A999, BASE!$A$4:$A$10003&""), 0)), "") | B1000: =IF(A1000="", "", VLOOKUP(A1000, BASE!$A$4:$B$10003, 2, FALSE)) | C1000: =IF(A1000="", "", SUMIF(BASE!$A$4:$A$10003, A1000, BASE!$C$4:$C$10003)) | D1000: =IF(A1000="", "", INDEX(BASE!$D$4:$D$10003, MATCH(A1000, BASE!$A$4:$A$10003, 0))) | E1000: =IF(A1000="", "", INDEX(BASE!$E$4:$E$10003, MATCH(A1000, BASE!$A$4:$A$10003, 0)))

Sheet EXTRATO
A1: CÓDIGO DE BARRAS | B1: PRODUTO | C1: QUANTIDADE | D1: DATA/HORA | E1: VEÍCULO | F1: STATUS
A2: =IFERROR(INDEX(BASE!$A$4:$A$10003, SMALL(IF(BASE!$F$4:$F$10003="CARREGADO", ROW(BASE!$A$4:$A$10003)-ROW(BASE!$A$4)+1), ROW(A1))), "") | B2: =IF(A2="", "", VLOOKUP(A2, BASE!$A$4:$B$10003, 2, FALSE)) | C2: =IF(A2="", "", VLOOKUP(A2, BASE!$A$4:$C$10003, 3, FALSE)) | D2: =IF(A2="", "", VLOOKUP(A2, BASE!$A$4:$D$10003, 4, FALSE)) | E2: =IF(A2="", "", VLOOKUP(A2, BASE!$A$4:$E$10003, 5, FALSE)) | F2: =IF(A2="", "", "CARREGADO")
A3: =IFERROR(INDEX(BASE!$A$4:$A$10003, SMALL(IF(BASE!$F$4:$F$10003="CARREGADO", ROW(BASE!$A$4:$A$10003)-ROW(BASE!$A$4)+1), ROW(A2))), "") | B3: =IF(A3="", "", VLOOKUP(A3, BASE!$A$4:$B$10003, 2, FALSE)) | C3: =IF(A3="", "", VLOOKUP(A3, BASE!$A$4:$C$10003, 3, FALSE)) | D3: =IF(A3="", "", VLOOKUP(A3, BASE!$A$4:$D$10003, 4, FALSE)) | E3: =IF(A3="", "", VLOOKUP(A3, BASE!$A$4:$E$10003, 5, FALSE)) | F3: =IF(A3="", "", "CARREGADO")
A4: =IFERROR(INDEX(BASE!$A$4:$A$10003, SMALL(IF(BASE!$F$4:$F$10003="CARREGADO", ROW(BASE!$A$4:$A$10003)-ROW(BASE!$A$4)+1), ROW(A3))), "") | B4: =IF(A4="", "", VLOOKUP(A4, BASE!$A$4:$B$10003, 2, FALSE)) | C4: =IF(A4="", "", VLOOKUP(A4, BASE!$A$4:$C$10003, 3, FALSE)) | D4: =IF(A4="", "", VLOOKUP(A4, BASE!$A$4:$D$10003, 4, FALSE)) | E4: =IF(A4="", "", VLOOKUP(A4, BASE!$A$4:$E$10003, 5, FALSE)) | F4: =IF(A4="", "", "CARREGADO")
A5: =IFERROR(INDEX(BASE!$A$4:$A$10003, SMALL(IF(BASE!$F$4:$F$10003="CARREGADO", ROW(BASE!$A$4:$A$10003)-ROW(BASE!$A$4)+1), ROW(A4))), "") | B5: =IF(A5="", "", VLOOKUP(A5, BASE!$A$4:$B$10003, 2, FALSE)) | C5: =IF(A5="", "", VLOOKUP(A5, BASE!$A$4:$C$10003, 3, FALSE)) | D5: =IF(A5="", "", VLOOKUP(A5, BASE!$A$4:$D$10003, 4, FALSE)) | E5: =IF(A5="", "", VLOOKUP(A5, BASE!$A$4:$E$10003, 5, FALSE)) | F5: =IF(A5="", "", "CARREGADO")
A6: =IFERROR(INDEX(BASE!$A$4:$A$10003, SMALL(IF(BASE!$F$4:$F$10003="CARREGADO", ROW(BASE!$A$4:$A$10003)-ROW(BASE!$A$4)+1), ROW(A5))), "") | B6: =IF(A6="", "", VLOOKUP(A6, BASE!$A$4:$B$10003, 2, FALSE)) | C6: =IF(A6="", "", VLOOKUP(A6, BASE!$A$4:$C$10003, 3, FALSE)) | D6: =IF(A6="", "", VLOOKUP(A6, BASE!$A$4:$D$10003, 4, FALSE)) | E6: =IF(A6="", "", VLOOKUP(A6, BASE!$A$4:$E$10003, 5, FALSE)) | F6: =IF(A6="", "", "CARREGADO")
A7: =IFERROR(INDEX(BASE!$A$4:$A$10003, SMALL(IF(BASE!$F$4:$F$10003="CARREGADO", ROW(BASE!$A$4:$A$10003)-ROW(BASE!$A$4)+1), ROW(A6))), "") | B7: =IF(A7="", "", VLOOKUP(A7, BASE!$A$4:$B$10003, 2, FALSE)) | C7: =IF(A7="", "", VLOOKUP(A7, BASE!$A$4:$C$10003, 3, FALSE)) | D7: =IF(A7="", "", VLOOKUP(A7, BASE!$A$4:$D$10003, 4, FALSE)) | E7: =IF(A7="", "", VLOOKUP(A7, BASE!$A$4:$E$10003, 5, FALSE)) | F7: =IF(A7="", "", "CARREGADO")
A8: =IFERROR(INDEX(BASE!$A$4:$A$10003, SMALL(IF(BASE!$F$4:$F$10003="CARREGADO", ROW(BASE!$A$4:$A$10003)-ROW(BASE!$A$4)+1), ROW(A7))), "") | B8: =IF(A8="", "", VLOOKUP(A8, BASE!$A$4:$B$10003, 2, FALSE)) | C8: =IF(A8="", "", VLOOKUP(A8, BASE!$A$4:$C$10003, 3, FALSE)) | D8: =IF(A8="", "", VLOOKUP(A8, BASE!$A$4:$D$10003, 4, FALSE)) | E8: =IF(A8="", "", VLOOKUP(A8, BASE!$A$4:$E$10003, 5, FALSE)) | F8: =IF(A8="", "", "CARREGADO")
A9: =IFERROR(INDEX(BASE!$A$4:$A$10003, SMALL(IF(BASE!$F$4:$F$10003="CARREGADO", ROW(BASE!$A$4:$A$10003)-ROW(BASE!$A$4)+1), ROW(A8))), "") | B9: =IF(A9="", "", VLOOKUP(A9, BASE!$A$4:$B$10003, 2, FALSE)) | C9: =IF(A9="", "", VLOOKUP(A9, BASE!$A$4:$C$10003, 3, FALSE)) | D9: =IF(A9="", "", VLOOKUP(A9, BASE!$A$4:$D$10003, 4, FALSE)) | E9: =IF(A9="", "", VLOOKUP(A9, BASE!$A$4:$E$10003, 5, FALSE)) | F9: =IF(A9="", "", "CARREGADO")
A10: =IFERROR(INDEX(BASE!$A$4:$A$10003, SMALL(IF(BASE!$F$4:$F$10003="CARREGADO", ROW(BASE!$A$4:$A$10003)-ROW(BASE!$A$4)+1), ROW(A9))), "") | B10: =IF(A10="", "", VLOOKUP(A10, BASE!$A$4:$B$10003, 2, FALSE)) | C10: =IF(A10="", "", VLOOKUP(A10, BASE!$A$4:$C$10003, 3, FALSE)) | D10: =IF(A10="", "", VLOOKUP(A10, BASE!$A$4:$D$10003, 4, FALSE)) | E10: =IF(A10="", "", VLOOKUP(A10, BASE!$A$4:$E$10003, 5, FALSE)) | F10: =IF(A10="", "", "CARREGADO")
A11: =IFERROR(INDEX(BASE!$A$4:$A$10003, SMALL(IF(BASE!$F$4:$F$10003="CARREGADO", ROW(BASE!$A$4:$A$10003)-ROW(BASE!$A$4)+1), ROW(A10))), "") | B11: =IF(A11="", "", VLOOKUP(A11, BASE!$A$4:$B$10003, 2, FALSE)) | C11: =IF(A11="", "", VLOOKUP(A11, BASE!$A$4:$C$10003, 3, FALSE)) | D11: =IF(A11="", "", VLOOKUP(A11, BASE!$A$4:$D$10003, 4, FALSE)) | E11: =IF(A11="", "", VLOOKUP(A11, BASE!$A$4:$E$10003, 5, FALSE)) | F11: =IF(A11="", "", "CARREGADO")
A12: =IFERROR(INDEX(BASE!$A$4:$A$10003, SMALL(IF(BASE!$F$4:$F$10003="CARREGADO", ROW(BASE!$A$4:$A$10003)-ROW(BASE!$A$4)+1), ROW(A11))), "") | B12: =IF(A12="", "", VLOOKUP(A12, BASE!$A$4:$B$10003, 2, FALSE)) | C12: =IF(A12="", "", VLOOKUP(A12, BASE!$A$4:$C$10003, 3, FALSE)) | D12: =IF(A12="", "", VLOOKUP(A12, BASE!$A$4:$D$10003, 4, FALSE)) | E12: =IF(A12="", "", VLOOKUP(A12, BASE!$A$4:$E$10003, 5, FALSE)) | F12: =IF(A12="", "", "CARREGADO")
A13: =IFERROR(INDEX(BASE!$A$4:$A$10003, SMALL(IF(BASE!$F$4:$F$10003="CARREGADO", ROW(BASE!$A$4:$A$10003)-ROW(BASE!$A$4)+1), ROW(A12))), "") | B13: =IF(A13="", "", VLOOKUP(A13, BASE!$A$4:$B$10003, 2, FALSE)) | C13: =IF(A13="", "", VLOOKUP(A13, BASE!$A$4:$C$10003, 3, FALSE)) | D13: =IF(A13="", "", VLOOKUP(A13, BASE!$A$4:$D$10003, 4, FALSE)) | E13: =IF(A13="", "", VLOOKUP(A13, BASE!$A$4:$E$10003, 5, FALSE)) | F13: =IF(A13="", "", "CARREGADO")
... A1000: =IFERROR(INDEX(BASE!$A$4:$A$10003, SMALL(IF(BASE!$F$4:$F$10003="CARREGADO", ROW(BASE!$A$4:$A$10003)-ROW(BASE!$A$4)+1), ROW(A999))), "") | B1000: =IF(A1000="", "", VLOOKUP(A1000, BASE!$A$4:$B$10003, 2, FALSE)) | C1000: =IF(A1000="", "", VLOOKUP(A1000, BASE!$A$4:$C$10003, 3, FALSE)) | D1000: =IF(A1000="", "", VLOOKUP(A1000, BASE!$A$4:$D$10003, 4, FALSE)) | E1000: =IF(A1000="", "", VLOOKUP(A1000, BASE!$A$4:$E$10003, 5, FALSE)) | F1000: =IF(A1000="", "", "CARREGADO")

Sheet COLABORADORES
A1: Centro de Custo | B1: Função | C1: Colaborador
A2: Armazenagem GRU | B2: Conferente | C2: ALEXANDRO BISPO SANTANA
A3: Armazenagem GRU | B3: coordenadora | C3: Astrogildo Rodrigues Dos S
A4: Armazenagem GRU | B4: Auxiliar de Logística | C4: BRUNO BARROS DE OLIVEIRA
A5: Armazenagem GRU | B5: Operador de Empilhadeira | C5: EDI CARLOS ROSENDE BORGES
A6: Armazenagem GRU | B6: aux de estoque | C6: Igor Gomes Dos Santos Rosa
A7: Armazenagem GRU | B7: Auxiliar de Logística | C7: ITALO MATHEUS PEREIRA LIMA CRUZ
A8: Armazenagem GRU | B8: aux de estoque | C8: Jorge Eduardo Rezende
A9: Armazenagem GRU | B9: coordenadora | C9: Joyce Cabral Do Nascimento
A10: Armazenagem GRU | B10: aux de estoque | C10: Leandro M Ferreira Dos Santos
A11: Armazenagem GRU | B11: aux de estoque | C11: Marcelo Silva De Medeiros
A12: Armazenagem GRU | B12: aux de estoque | C12: Marcone Gomes Do Nascimento
... A61: Transporte GRU | B61: Yuri Ravell Feitoza do Nascimento | C61: YURI RAVELL FEITOZA DO NASCIMENTO
B65: 46056
B66: 46145
B67: 89

Sheet ROMANEIO POR ITEM
A1: Data de cadastro | B1: Id roteiro | C1: Identificador da rota | D1: Id viagem faturada | E1: Entrega estimada | F1: Placa | G1: Pedido | H1: Código cliente | I1: Cliente | J1: Tipo cliente | K1: Transportadora | L1: Endereço | M1: Bairro | N1: Cidade | O1: Código do produto | P1: Descrição do produto | Q1: Quantidade do produto | R1: Qtd. caixas | S1: Unidade de medida do produto | T1: Peso bruto pedido | U1: Início previsto | V1: Unidade | W1: Valor total pedido | X1: Peso do veículo | Y1: Motorista
A2: 46066.424 | B2: 555555 | C2: 14 - PPY - VARGINHA | D2: 555555 | F2: ULP0002 | G2: 9999999 | H2: 47380171000157 | I2: CD Guarulhos (Ultrapão) | K2: Ultrapão Transportes | L2: Avenida Faustino Ramalho | M2: Vila Galvão | N2: Guarulhos | O2: 3000 | P2: kit baloes | Q2: 3 | S2: CX | T2: 2.5 | U2: 46069.292 | V2: CD Pouso Alegre Ultrapão | W2: 0 | X2: 28000 | Y2: Diego
A3: 46066.424 | B3: 555555 | C3: 14 - PPY - VARGINHA | D3: 555555 | E3: 46065.548 | F3: ULP0002 | G3: 9999999 | H3: 47380171000157 | I3: CD Guarulhos (Ultrapão) | K3: Ultrapão Transportes | L3: Avenida Faustino Ramalho | M3: Vila Galvão | N3: Guarulhos | O3: 2000 | P3: GRAMPEADOR | Q3: 10 | S3: CX | T3: 3.2 | U3: 46069.292 | V3: CD Pouso Alegre Ultrapão | W3: 0 | X3: 28000 | Y3: Diego
A4: 46071.487 | B4: 641160 | C4: 36 - GRU - ACLIMAÇÃO | D4: 18711426 | E4: 46071.609 | F4: SEG0002 | G4: 1722430201 | H4: 26563652080059 | I4: OXXO BETO | J4: Oxxo | K4: Ultrapão Transportes | L4: RUA ASTORGA, 482 LOJA CJ 460 R JANDAIA SUL | M4: VILA GUILHERMINA | N4: São Paulo | O4: 01.01.0001 | P4: MASSA CONGELADA DE PAO FRANCES RAPIDA - 5KG | Q4: 40 | R4: 0 | S4: PT | T4: 0 | U4: 46071.417 | V4: CD Guarulhos Ultrapão (Distribuidora) | W4: 0 | X4: 4000 | Y4: Vicente Varela da Silva Junior
A5: 46071.487 | B5: 641160 | C5: 36 - GRU - ACLIMAÇÃO | D5: 18711426 | E5: 46071.609 | F5: SEG0002 | G5: 1722430201 | H5: 26563652080059 | I5: OXXO BETO | J5: Oxxo | K5: Ultrapão Transportes | L5: RUA ASTORGA, 482 LOJA CJ 460 R JANDAIA SUL | M5: VILA GUILHERMINA | N5: São Paulo | O5: 01.09.0012 | P5: PAO FRANCES HOMEBAKE 3,24KG - 12 UNIDADES 270G | Q5: 1 | R5: 0 | S5: CX | T5: 0 | U5: 46071.417 | V5: CD Guarulhos Ultrapão (Distribuidora) | W5: 0 | X5: 4000 | Y5: Vicente Varela da Silva Junior
A6: 46071.739 | B6: 641511 | C6: 64 - GRU - SÃO CAETANO DO SUL | E6: 46070.857 | F6: SEG0001 | G6: 1714870201 | H6: 26563652046705 | I6: OXXO AMAROI | J6: Oxxo | K6: Ultrapão Transportes | L6: R AMAZONAS, 422 | M6: Centro | N6: São Caetano do Sul | O6: 01.01.0001 | P6: MASSA CONGELADA DE PAO FRANCES RAPIDA - 5KG | Q6: 7 | R6: 10 | S6: PT | T6: 57.336 | U6: 46072.292 | V6: CD Guarulhos Ultrapão (Distribuidora) | W6: 717.31 | X6: 4000 | Y6: Joaquim Martins dos Santos
A7: 46071.739 | B7: 641511 | C7: 64 - GRU - SÃO CAETANO DO SUL | E7: 46070.857 | F7: SEG0001 | G7: 1714870201 | H7: 26563652046705 | I7: OXXO AMAROI | J7: Oxxo | K7: Ultrapão Transportes | L7: R AMAZONAS, 422 | M7: Centro | N7: São Caetano do Sul | O7: 01.02.0007 | P7: MASSA CONGELADA DE PAO FRANCES COM GRAOS RAPIDA - 5KG | Q7: 1 | R7: 10 | S7: PT | T7: 57.336 | U7: 46072.292 | V7: CD Guarulhos Ultrapão (Distribuidora) | W7: 717.31 | X7: 4000 | Y7: Joaquim Martins dos Santos
A8: 46071.739 | B8: 641511 | C8: 64 - GRU - SÃO CAETANO DO SUL | E8: 46070.857 | F8: SEG0001 | G8: 1714870201 | H8: 26563652046705 | I8: OXXO AMAROI | J8: Oxxo | K8: Ultrapão Transportes | L8: R AMAZONAS, 422 | M8: Centro | N8: São Caetano do Sul | O8: 01.04.0008 | P8: PAO DE QUEIJO EMPANADO 30G - CX 10KG | Q8: 1 | R8: 10 | S8: CX | T8: 57.336 | U8: 46072.292 | V8: CD Guarulhos Ultrapão (Distribuidora) | W8: 717.31 | X8: 4000 | Y8: Joaquim Martins dos Santos
A9: 46071.739 | B9: 641511 | C9: 64 - GRU - SÃO CAETANO DO SUL | E9: 46070.857 | F9: SEG0001 | G9: 1714870201 | H9: 26563652046705 | I9: OXXO AMAROI | J9: Oxxo | K9: Ultrapão Transportes | L9: R AMAZONAS, 422 | M9: Centro | N9: São Caetano do Sul | O9: 02.01.0005 | P9: PAO DE QUEIJO FORNO DE MINAS ASSADO CONGELADO MAX LANCHE | Q9: 1 | R9: 10 | S9: CX | T9: 57.336 | U9: 46072.292 | V9: CD Guarulhos Ultrapão (Distribuidora) | W9: 717.31 | X9: 4000 | Y9: Joaquim Martins dos Santos
A10: 46071.739 | B10: 641511 | C10: 64 - GRU - SÃO CAETANO DO SUL | E10: 46072.773 | F10: SEG0001 | G10: 1725780201 | H10: 26563652029703 | I10: OXXO ATELIER | J10: Oxxo | K10: Ultrapão Transportes | L10: R SAO PAULO, 881 | M10: Santo Antônio | N10: São Caetano do Sul | O10: 01.01.0001 | P10: MASSA CONGELADA DE PAO FRANCES RAPIDA - 5KG | Q10: 14 | R10: 0 | S10: PT | T10: 70.252 | U10: 46072.292 | V10: CD Guarulhos Ultrapão (Distribuidora) | W10: 478.66 | X10: 4000 | Y10: Joaquim Martins dos Santos
A11: 46071.739 | B11: 641511 | C11: 64 - GRU - SÃO CAETANO DO SUL | E11: 46072.773 | F11: SEG0001 | G11: 1723350201 | H11: 26563652040006 | I11: OXXO BETTIN | J11: Oxxo | K11: Ultrapão Transportes | L11: R COSTA BARROS, 1890 | M11: Parque São Lucas | N11: São Paulo | O11: 01.01.0001 | P11: MASSA CONGELADA DE PAO FRANCES RAPIDA - 5KG | Q11: 9 | R11: 0 | S11: PT | T11: 50.162 | U11: 46072.292 | V11: CD Guarulhos Ultrapão (Distribuidora) | W11: 356.72 | X11: 4000 | Y11: Joaquim Martins dos Santos
A12: 46071.739 | B12: 641511 | C12: 64 - GRU - SÃO CAETANO DO SUL | E12: 46072.773 | F12: SEG0001 | G12: 1723350201 | H12: 26563652040006 | I12: OXXO BETTIN | J12: Oxxo | K12: Ultrapão Transportes | L12: R COSTA BARROS, 1890 | M12: Parque São Lucas | N12: São Paulo | O12: 01.02.0007 | P12: MASSA CONGELADA DE PAO FRANCES COM GRAOS RAPIDA - 5KG | Q12: 1 | R12: 0 | S12: PT | T12: 50.162 | U12: 46072.292 | V12: CD Guarulhos Ultrapão (Distribuidora) | W12: 356.72 | X12: 4000 | Y12: Joaquim Martins dos Santos
A13: 46071.739 | B13: 641511 | C13: 64 - GRU - SÃO CAETANO DO SUL | E13: 46072.773 | F13: SEG0001 | G13: 1723430201 | H13: 26563652067540 | I13: OXXO PORFIRIO DA PAZ | J13: Oxxo | K13: Ultrapão Transportes | M13: Vila Bancaria | N13: São Paulo | O13: 01.01.0001 | P13: MASSA CONGELADA DE PAO FRANCES RAPIDA - 5KG | Q13: 3 | R13: 0 | S13: PT | T13: 25.684 | U13: 46072.292 | V13: CD Guarulhos Ultrapão (Distribuidora) | W13: 363.57 | X13: 4000 | Y13: Joaquim Martins dos Santos
A14: 46071.739 | B14: 641511 | C14: 64 - GRU - SÃO CAETANO DO SUL | E14: 46072.773 | F14: SEG0001 | G14: 1723430201 | H14: 26563652067540 | I14: OXXO PORFIRIO DA PAZ | J14: Oxxo | K14: Ultrapão Transportes | M14: Vila Bancaria | N14: São Paulo | O14: 01.04.0066 | P14: MASSA CONGELADA DE PÃO DE QUEIJO RECHEADO DE REQUEIJÃO 65G ? CX 10 KG ? 5 UN DE 2 KG | Q14: 1 | R14: 0 | S14: CX | T14: 25.684 | U14: 46072.292 | V14: CD Guarulhos Ultrapão (Distribuidora) | W14: 363.57 | X14: 4000 | Y14: Joaquim Martins dos Santos
A15: 46071.739 | B15: 641511 | C15: 64 - GRU - SÃO CAETANO DO SUL | E15: 46072.773 | F15: SEG0001 | G15: 1725940201 | H15: 26563652032674 | I15: OXXO SERAFIM ESTACAO | J15: Oxxo | K15: Ultrapão Transportes | M15: Centro | N15: São Caetano do Sul | O15: 01.01.0001 | P15: MASSA CONGELADA DE PAO FRANCES RAPIDA - 5KG | Q15: 10 | R15: 0 | S15: PT | T15: 50.18 | U15: 46072.292 | V15: CD Guarulhos Ultrapão (Distribuidora) | W15: 341.9 | X15: 4000 | Y15: Joaquim Martins dos Santos
A16: 46071.739 | B16: 641511 | C16: 64 - GRU - SÃO CAETANO DO SUL | E16: 46072.773 | F16: SEG0001 | G16: 1724030201 | H16: 26563652045300 | I16: OXXO ANTERO | J16: Oxxo | K16: Ultrapão Transportes | L16: RUA DOMINGOS AFONSO, 398 | M16: Santa Clara | N16: São Paulo | O16: 01.01.0001 | P16: MASSA CONGELADA DE PAO FRANCES RAPIDA - 5KG | Q16: 9 | R16: 0 | S16: PT | T16: 50.162 | U16: 46072.292 | V16: CD Guarulhos Ultrapão (Distribuidora) | W16: 356.72 | X16: 4000 | Y16: Joaquim Martins dos Santos
A17: 46071.739 | B17: 641511 | C17: 64 - GRU - SÃO CAETANO DO SUL | E17: 46072.773 | F17: SEG0001 | G17: 1724030201 | H17: 26563652045300 | I17: OXXO ANTERO | J17: Oxxo | K17: Ultrapão Transportes | L17: RUA DOMINGOS AFONSO, 398 | M17: Santa Clara | N17: São Paulo | O17: 01.02.0007 | P17: MASSA CONGELADA DE PAO FRANCES COM GRAOS RAPIDA - 5KG | Q17: 1 | R17: 0 | S17: PT | T17: 50.162 | U17: 46072.292 | V17: CD Guarulhos Ultrapão (Distribuidora) | W17: 356.72 | X17: 4000 | Y17: Joaquim Martins dos Santos
A18: 46071.739 | B18: 641511 | C18: 64 - GRU - SÃO CAETANO DO SUL | E18: 46072.773 | F18: SEG0001 | G18: 1726120201 | H18: 26563652060023 | I18: OXXO FATIMA CAETANO | J18: Oxxo | K18: Ultrapão Transportes | M18: Santa Paula | N18: São Caetano do Sul | O18: 01.01.0001 | P18: MASSA CONGELADA DE PAO FRANCES RAPIDA - 5KG | Q18: 8 | R18: 0 | S18: PT | T18: 52.354 | U18: 46072.292 | V18: CD Guarulhos Ultrapão (Distribuidora) | W18: 576.78 | X18: 4000 | Y18: Joaquim Martins dos Santos
A19: 46071.739 | B19: 641511 | C19: 64 - GRU - SÃO CAETANO DO SUL | E19: 46072.773 | F19: SEG0001 | G19: 1726120201 | H19: 26563652060023 | I19: OXXO FATIMA CAETANO | J19: Oxxo | K19: Ultrapão Transportes | M19: Santa Paula | N19: São Caetano do Sul | O19: 01.02.0007 | P19: MASSA CONGELADA DE PAO FRANCES COM GRAOS RAPIDA - 5KG | Q19: 1 | R19: 0 | S19: PT | T19: 52.354 | U19: 46072.292 | V19: CD Guarulhos Ultrapão (Distribuidora) | W19: 576.78 | X19: 4000 | Y19: Joaquim Martins dos Santos
A20: 46071.739 | B20: 641511 | C20: 64 - GRU - SÃO CAETANO DO SUL | E20: 46072.773 | F20: SEG0001 | G20: 1726120201 | H20: 26563652060023 | I20: OXXO FATIMA CAETANO | J20: Oxxo | K20: Ultrapão Transportes | M20: Santa Paula | N20: São Caetano do Sul | O20: 02.01.0005 | P20: PAO DE QUEIJO FORNO DE MINAS ASSADO CONGELADO MAX LANCHE | Q20: 1 | R20: 0 | S20: CX | T20: 52.354 | U20: 46072.292 | V20: CD Guarulhos Ultrapão (Distribuidora) | W20: 576.78 | X20: 4000 | Y20: Joaquim Martins dos Santos
A21: 46071.739 | B21: 641511 | C21: 64 - GRU - SÃO CAETANO DO SUL | E21: 46072.773 | F21: SEG0001 | G21: 1726140201 | H21: 26563652038109 | I21: OXXO GOIAS CAFE | J21: Oxxo | K21: Ultrapão Transportes | M21: Santo Antônio | N21: São Caetano do Sul | O21: 01.01.0001 | P21: MASSA CONGELADA DE PAO FRANCES RAPIDA - 5KG | Q21: 6 | R21: 0 | S21: PT | T21: 40.108 | U21: 46072.292 | V21: CD Guarulhos Ultrapão (Distribuidora) | W21: 379.86 | X21: 4000 | Y21: Joaquim Martins dos Santos
A22: 46071.739 | B22: 641511 | C22: 64 - GRU - SÃO CAETANO DO SUL | E22: 46072.773 | F22: SEG0001 | G22: 1726140201 | H22: 26563652038109 | I22: OXXO GOIAS CAFE | J22: Oxxo | K22: Ultrapão Transportes | M22: Santo Antônio | N22: São Caetano do Sul | O22: 01.04.0008 | P22: PAO DE QUEIJO EMPANADO 30G - CX 10KG | Q22: 1 | R22: 0 | S22: CX | T22: 40.108 | U22: 46072.292 | V22: CD Guarulhos Ultrapão (Distribuidora) | W22: 379.86 | X22: 4000 | Y22: Joaquim Martins dos Santos
A23: 46071.739 | B23: 641511 | C23: 64 - GRU - SÃO CAETANO DO SUL | E23: 46072.773 | F23: SEG0001 | G23: 1724290201 | H23: 26563652019147 | I23: OXXO SOLIDONIO | J23: Oxxo | K23: Ultrapão Transportes | M23: Vila Ema | N23: São Paulo | O23: 01.01.0001 | P23: MASSA CONGELADA DE PAO FRANCES RAPIDA - 5KG | Q23: 4 | R23: 0 | S23: PT | T23: 25.072 | U23: 46072.292 | V23: CD Guarulhos Ultrapão (Distribuidora) | W23: 185.77 | X23: 4000 | Y23: Joaquim Martins dos Santos
A24: 46071.739 | B24: 641511 | C24: 64 - GRU - SÃO CAETANO DO SUL | E24: 46072.773 | F24: SEG0001 | G24: 1724290201 | H24: 26563652019147 | I24: OXXO SOLIDONIO | J24: Oxxo | K24: Ultrapão Transportes | M24: Vila Ema | N24: São Paulo | O24: 01.02.0007 | P24: MASSA CONGELADA DE PAO FRANCES COM GRAOS RAPIDA - 5KG | Q24: 1 | R24: 0 | S24: PT | T24: 25.072 | U24: 46072.292 | V24: CD Guarulhos Ultrapão (Distribuidora) | W24: 185.77 | X24: 4000 | Y24: Joaquim Martins dos Santos
A25: 46071.739 | B25: 641511 | C25: 64 - GRU - SÃO CAETANO DO SUL | E25: 46072.773 | F25: SEG0001 | G25: 1724430201 | H25: 26563652077260 | I25: OXXO PLANALTO CRUZ | J25: Oxxo | K25: Ultrapão Transportes | M25: JARDIM ADUTORA | N25: São Paulo | O25: 01.01.0001 | P25: MASSA CONGELADA DE PAO FRANCES RAPIDA - 5KG | Q25: 9 | R25: 0 | S25: PT | T25: 48.362 | U25: 46072.292 | V25: CD Guarulhos Ultrapão (Distribuidora) | W25: 373.71 | X25: 4000 | Y25: Joaquim Martins dos Santos
A26: 46071.739 | B26: 641511 | C26: 64 - GRU - SÃO CAETANO DO SUL | E26: 46072.773 | F26: SEG0001 | G26: 1724430201 | H26: 26563652077260 | I26: OXXO PLANALTO CRUZ | J26: Oxxo | K26: Ultrapão Transportes | M26: JARDIM ADUTORA | N26: São Paulo | O26: 01.10.0013 | P26: MINI BAGUETE FRANCESA LEVIASSA - PT 0,240 KG - CX 2,88 KG - 12 UN | Q26: 1 | R26: 0 | S26: CX | T26: 48.362 | U26: 46072.292 | V26: CD Guarulhos Ultrapão (Distribuidora) | W26: 373.71 | X26: 4000 | Y26: Joaquim Martins dos Santos
A27: 46071.739 | B27: 641511 | C27: 64 - GRU - SÃO CAETANO DO SUL | E27: 46072.773 | F27: SEG0001 | G27: 1726350201 | H27: 26563652028642 | I27: OXXO MONTE ALEGRE | J27: Oxxo | K27: Ultrapão Transportes | M27: Santo Antônio | N27: São Caetano do Sul | O27: 01.01.0001 | P27: MASSA CONGELADA DE PAO FRANCES RAPIDA - 5KG | Q27: 8 | R27: 0 | S27: PT | T27: 50.144 | U27: 46072.292 | V27: CD Guarulhos Ultrapão (Distribuidora) | W27: 371.54 | X27: 4000 | Y27: Joaquim Martins dos Santos
A28: 46071.739 | B28: 641511 | C28: 64 - GRU - SÃO CAETANO DO SUL | E28: 46072.773 | F28: SEG0001 | G28: 1726350201 | H28: 26563652028642 | I28: OXXO MONTE ALEGRE | J28: Oxxo | K28: Ultrapão Transportes | M28: Santo Antônio | N28: São Caetano do Sul | O28: 01.02.0007 | P28: MASSA CONGELADA DE PAO FRANCES COM GRAOS RAPIDA - 5KG | Q28: 2 | R28: 0 | S28: PT | T28: 50.144 | U28: 46072.292 | V28: CD Guarulhos Ultrapão (Distribuidora) | W28: 371.54 | X28: 4000 | Y28: Joaquim Martins dos Santos
A29: 46071.739 | B29: 641511 | C29: 64 - GRU - SÃO CAETANO DO SUL | E29: 46072.773 | F29: SEG0001 | G29: 1726370201 | H29: 26563652046705 | I29: OXXO AMAROI | J29: Oxxo | K29: Ultrapão Transportes | L29: R AMAZONAS, 422 | M29: Centro | N29: São Caetano do Sul | O29: 01.01.0001 | P29: MASSA CONGELADA DE PAO FRANCES RAPIDA - 5KG | Q29: 5 | R29: 0 | S29: PT | T29: 42.06 | U29: 46072.292 | V29: CD Guarulhos Ultrapão (Distribuidora) | W29: 535.37 | X29: 4000 | Y29: Joaquim Martins dos Santos
A30: 46071.739 | B30: 641511 | C30: 64 - GRU - SÃO CAETANO DO SUL | E30: 46072.773 | F30: SEG0001 | G30: 1726370201 | H30: 26563652046705 | I30: OXXO AMAROI | J30: Oxxo | K30: Ultrapão Transportes | L30: R AMAZONAS, 422 | M30: Centro | N30: São Caetano do Sul | O30: 01.02.0007 | P30: MASSA CONGELADA DE PAO FRANCES COM GRAOS RAPIDA - 5KG | Q30: 2 | R30: 0 | S30: PT | T30: 42.06 | U30: 46072.292 | V30: CD Guarulhos Ultrapão (Distribuidora) | W30: 535.37 | X30: 4000 | Y30: Joaquim Martins dos Santos
A31: 46071.739 | B31: 641511 | C31: 64 - GRU - SÃO CAETANO DO SUL | E31: 46072.773 | F31: SEG0001 | G31: 1726370201 | H31: 26563652046705 | I31: OXXO AMAROI | J31: Oxxo | K31: Ultrapão Transportes | L31: R AMAZONAS, 422 | M31: Centro | N31: São Caetano do Sul | O31: 02.01.0004 | P31: PAO DE QUEIJO FORNO DE MINAS ASSADO CONGELADO RECHEADO REQUEIJAO MAX LANCHE | Q31: 1 | R31: 0 | S31: CX | T31: 42.06 | U31: 46072.292 | V31: CD Guarulhos Ultrapão (Distribuidora) | W31: 535.37 | X31: 4000 | Y31: Joaquim Martins dos Santos
A32: 46071.739 | B32: 641511 | C32: 64 - GRU - SÃO CAETANO DO SUL | E32: 46072.773 | F32: SEG0001 | G32: 1726510201 | H32: 26563652079395 | I32: OXXO QUINTINO GOIAS | J32: Oxxo | K32: Ultrapão Transportes | M32: Barcelona | N32: São Caetano do Sul | O32: 01.01.0001 | P32: MASSA CONGELADA DE PAO FRANCES RAPIDA - 5KG | Q32: 5 | R32: 0 | S32: PT | T32: 42.06 | U32: 46072.292 | V32: CD Guarulhos Ultrapão (Distribuidora) | W32: 612.07 | X32: 4000 | Y32: Joaquim Martins dos Santos
A33: 46071.739 | B33: 641511 | C33: 64 - GRU - SÃO CAETANO DO SUL | E33: 46072.773 | F33: SEG0001 | G33: 1726510201 | H33: 26563652079395 | I33: OXXO QUINTINO GOIAS | J33: Oxxo | K33: Ultrapão Transportes | M33: Barcelona | N33: São Caetano do Sul | O33: 01.04.0008 | P33: PAO DE QUEIJO EMPANADO 30G - CX 10KG | Q33: 1 | R33: 0 | S33: CX | T33: 42.06 | U33: 46072.292 | V33: CD Guarulhos Ultrapão (Distribuidora) | W33: 612.07 | X33: 4000 | Y33: Joaquim Martins dos Santos
A34: 46071.739 | B34: 641511 | C34: 64 - GRU - SÃO CAETANO DO SUL | E34: 46072.773 | F34: SEG0001 | G34: 1726510201 | H34: 26563652079395 | I34: OXXO QUINTINO GOIAS | J34: Oxxo | K34: Ultrapão Transportes | M34: Barcelona | N34: São Caetano do Sul | O34: 02.01.0004 | P34: PAO DE QUEIJO FORNO DE MINAS ASSADO CONGELADO RECHEADO REQUEIJAO MAX LANCHE | Q34: 1 | R34: 0 | S34: CX | T34: 42.06 | U34: 46072.292 | V34: CD Guarulhos Ultrapão (Distribuidora) | W34: 612.07 | X34: 4000 | Y34: Joaquim Martins dos Santos
A35: 46071.739 | B35: 641511 | C35: 64 - GRU - SÃO CAETANO DO SUL | E35: 46072.773 | F35: SEG0001 | G35: 1726530201 | H35: 26563652059793 | I35: OXXO HELO SALGADO | J35: Oxxo | K35: Ultrapão Transportes | M35: Fundação, | N35: São Caetano do Sul | O35: 01.01.0001 | P35: MASSA CONGELADA DE PAO FRANCES RAPIDA - 5KG | Q35: 3 | R35: 0 | S35: PT | T35: 40.684 | U35: 46072.292 | V35: CD Guarulhos Ultrapão (Distribuidora) | W35: 510.6 | X35: 4000 | Y35: Joaquim Martins dos Santos
A36: 46071.739 | B36: 641511 | C36: 64 - GRU - SÃO CAETANO DO SUL | E36: 46072.773 | F36: SEG0001 | G36: 1726530201 | H36: 26563652059793 | I36: OXXO HELO SALGADO | J36: Oxxo | K36: Ultrapão Transportes | M36: Fundação, | N36: São Caetano do Sul | O36: 01.02.0007 | P36: MASSA CONGELADA DE PAO FRANCES COM GRAOS RAPIDA - 5KG | Q36: 3 | R36: 0 | S36: PT | T36: 40.684 | U36: 46072.292 | V36: CD Guarulhos Ultrapão (Distribuidora) | W36: 510.6 | X36: 4000 | Y36: Joaquim Martins dos Santos
A37: 46071.739 | B37: 641511 | C37: 64 - GRU - SÃO CAETANO DO SUL | E37: 46072.773 | F37: SEG0001 | G37: 1726530201 | H37: 26563652059793 | I37: OXXO HELO SALGADO | J37: Oxxo | K37: Ultrapão Transportes | M37: Fundação, | N37: São Caetano do Sul | O37: 01.04.0066 | P37: MASSA CONGELADA DE PÃO DE QUEIJO RECHEADO DE REQUEIJÃO 65G ? CX 10 KG ? 5 UN DE 2 KG | Q37: 1 | R37: 0 | S37: CX | T37: 40.684 | U37: 46072.292 | V37: CD Guarulhos Ultrapão (Distribuidora) | W37: 510.6 | X37: 4000 | Y37: Joaquim Martins dos Santos
A38: 46071.739 | B38: 641512 | C38: GRU - CD CONFIANÇA | E38: 46070.797 | F38: ELQ2549 | G38: 1708280201 | H38: 53045266000389 | I38: REDE CONFIANÇA DEPOSITO CENTRAL LJ 100 | J38: Varejo | K38: Wesley Odilon Ribeiro | L38: RUA INACIO CONCEICAO VEIRA, 25-75 | M38: VILA AVIACAO | N38: Bauru | O38: 01.09.0007 | P38: CIABATTA HOMEBAKE TRADICIONAL 3,6KG - 12 UNIDADES 300G | Q38: 34 | R38: 0 | S38: CX | T38: 548.16 | U38: 46072.292 | V38: CD Guarulhos Ultrapão (Distribuidora) | W38: 12403.44 | X38: 2500 | Y38: Wesley Odilon Ribeiro
A39: 46071.739 | B39: 641512 | C39: GRU - CD CONFIANÇA | E39: 46070.797 | F39: ELQ2549 | G39: 1708280201 | H39: 53045266000389 | I39: REDE CONFIANÇA DEPOSITO CENTRAL LJ 100 | J39: Varejo | K39: Wesley Odilon Ribeiro | L39: RUA INACIO CONCEICAO VEIRA, 25-75 | M39: VILA AVIACAO | N39: Bauru | O39: 01.09.0008 | P39: CIABATTA HOMEBAKE COM GRAOS 3,6KG - 12 UNIDADES 300G | Q39: 32 | R39: 0 | S39: CX | T39: 548.16 | U39: 46072.292 | V39: CD Guarulhos Ultrapão (Distribuidora) | W39: 12403.44 | X39: 2500 | Y39: Wesley Odilon Ribeiro
A40: 46071.739 | B40: 641512 | C40: GRU - CD CONFIANÇA | E40: 46070.797 | F40: ELQ2549 | G40: 1708280201 | H40: 53045266000389 | I40: REDE CONFIANÇA DEPOSITO CENTRAL LJ 100 | J40: Varejo | K40: Wesley Odilon Ribeiro | L40: RUA INACIO CONCEICAO VEIRA, 25-75 | M40: VILA AVIACAO | N40: Bauru | O40: 01.09.0012 | P40: PAO FRANCES HOMEBAKE 3,24KG - 12 UNIDADES 270G | Q40: 72 | R40: 0 | S40: CX | T40: 548.16 | U40: 46072.292 | V40: CD Guarulhos Ultrapão (Distribuidora) | W40: 12403.44 | X40: 2500 | Y40: Wesley Odilon Ribeiro
A41: 46071.739 | B41: 641513 | C41: 121 - GRU - LITORAL | E41: 46072.773 | F41: SVZ2D07 | G41: 1724710201 | H41: 26563652053167 | I41: OXXO BOLIVIA | J41: Oxxo | K41: Ultrapão Transportes | L41: RUA BOLIVIA, 219 | M41: Guilhermina | N41: Praia Grande | O41: 01.01.0001 | P41: MASSA CONGELADA DE PAO FRANCES RAPIDA - 5KG | Q41: 9 | R41: 0 | S41: PT | T41: 48.362 | U41: 46072.292 | V41: CD Guarulhos Ultrapão (Distribuidora) | W41: 373.71 | X41: 4200 | Y41: Luciano Domenices
A42: 46071.739 | B42: 641513 | C42: 121 - GRU - LITORAL | E42: 46072.773 | F42: SVZ2D07 | G42: 1724710201 | H42: 26563652053167 | I42: OXXO BOLIVIA | J42: Oxxo | K42: Ultrapão Transportes | L42: RUA BOLIVIA, 219 | M42: Guilhermina | N42: Praia Grande | O42: 01.10.0014 | P42: CIABATTA TRADICIONAL LEVIASSA- PT 0,220 KG- CX 2,64 KG- 12 UN | Q42: 1 | R42: 0 | S42: CX | T42: 48.362 | U42: 46072.292 | V42: CD Guarulhos Ultrapão (Distribuidora) | W42: 373.71 | X42: 4200 | Y42: Luciano Domenices
A43: 46071.739 | B43: 641513 | C43: 121 - GRU - LITORAL | E43: 46072.773 | F43: SVZ2D07 | G43: 1724730201 | H43: 26563652058207 | I43: OXXO GONCALO MONTEIRO | J43: Oxxo | K43: Ultrapão Transportes | M43: Centro, | N43: São Vicente | O43: 01.01.0001 | P43: MASSA CONGELADA DE PAO FRANCES RAPIDA - 5KG | Q43: 12 | R43: 0 | S43: PT | T43: 65.216 | U43: 46072.292 | V43: CD Guarulhos Ultrapão (Distribuidora) | W43: 459.29 | X43: 4200 | Y43: Luciano Domenices
A44: 46071.739 | B44: 641513 | C44: 121 - GRU - LITORAL | E44: 46072.773 | F44: SVZ2D07 | G44: 1724730201 | H44: 26563652058207 | I44: OXXO GONCALO MONTEIRO | J44: Oxxo | K44: Ultrapão Transportes | M44: Centro, | N44: São Vicente | O44: 01.02.0007 | P44: MASSA CONGELADA DE PAO FRANCES COM GRAOS RAPIDA - 5KG | Q44: 1 | R44: 0 | S44: PT | T44: 65.216 | U44: 46072.292 | V44: CD Guarulhos Ultrapão (Distribuidora) | W44: 459.29 | X44: 4200 | Y44: Luciano Domenices
A45: 46071.739 | B45: 641513 | C45: 121 - GRU - LITORAL | E45: 46072.773 | F45: SVZ2D07 | G45: 1724750201 | H45: 26563652083821 | I45: OXXO ANTIBES | J45: Oxxo | K45: Ultrapão Transportes | L45: Avenida Dom Pedro I | M45: ENSEADA | N45: Guaruja | O45: 01.01.0001 | P45: MASSA CONGELADA DE PAO FRANCES RAPIDA - 5KG | Q45: 7 | R45: 0 | S45: PT | T45: 45.126 | U45: 46072.292 | V45: CD Guarulhos Ultrapão (Distribuidora) | W45: 414.05 | X45: 4200 | Y45: Luciano Domenices
A46: 46071.739 | B46: 641513 | C46: 121 - GRU - LITORAL | E46: 46072.773 | F46: SVZ2D07 | G46: 1724750201 | H46: 26563652083821 | I46: OXXO ANTIBES | J46: Oxxo | K46: Ultrapão Transportes | L46: Avenida Dom Pedro I | M46: ENSEADA | N46: Guaruja | O46: 01.04.0008 | P46: PAO DE QUEIJO EMPANADO 30G - CX 10KG | Q46: 1 | R46: 0 | S46: CX | T46: 45.126 | U46: 46072.292 | V46: CD Guarulhos Ultrapão (Distribuidora) | W46: 414.05 | X46: 4200 | Y46: Luciano Domenices
A47: 46071.739 | B47: 641513 | C47: 121 - GRU - LITORAL | E47: 46072.773 | F47: SVZ2D07 | G47: 1724800201 | H47: 26563652055453 | I47: OXXO DUQUE MAR | J47: Oxxo | K47: Ultrapão Transportes | M47: Boqueirão | N47: Praia Grande | O47: 01.01.0001 | P47: MASSA CONGELADA DE PAO FRANCES RAPIDA - 5KG | Q47: 5 | R47: 0 | S47: PT | T47: 25.09 | U47: 46072.292 | V47: CD Guarulhos Ultrapão (Distribuidora) | W47: 170.95 | X47: 4200 | Y47: Luciano Domenices
A48: 46071.739 | B48: 641513 | C48: 121 - GRU - LITORAL | E48: 46072.773 | F48: SVZ2D07 | G48: 1725340201 | H48: 26563652063472 | I48: OXXO CARVALHO | J48: Oxxo | K48: Ultrapão Transportes | L48: RUA DOUTOR CARVALHO DE MENDONCA - 453 - LOJA A, SN | M48: Vila Belmiro | N48: Santos | O48: 01.02.0007 | P48: MASSA CONGELADA DE PAO FRANCES COM GRAOS RAPIDA - 5KG | Q48: 2 | R48: 0 | S48: PT | T48: 12.5 | U48: 46072.292 | V48: CD Guarulhos Ultrapão (Distribuidora) | W48: 199.82 | X48: 4200 | Y48: Luciano Domenices
A49: 46071.739 | B49: 641513 | C49: 121 - GRU - LITORAL | E49: 46072.773 | F49: SVZ2D07 | G49: 1725340201 | H49: 26563652063472 | I49: OXXO CARVALHO | J49: Oxxo | K49: Ultrapão Transportes | L49: RUA DOUTOR CARVALHO DE MENDONCA - 453 - LOJA A, SN | M49: Vila Belmiro | N49: Santos | O49: 02.03.0041 | P49: BOLO DE CENOURA C/ COBERTURA - 2UN | Q49: 1 | R49: 0 | S49: CX | T49: 12.5 | U49: 46072.292 | V49: CD Guarulhos Ultrapão (Distribuidora) | W49: 199.82 | X49: 4200 | Y49: Luciano Domenices
A50: 46071.739 | B50: 641513 | C50: 121 - GRU - LITORAL | E50: 46072.773 | F50: SVZ2D07 | G50: 1722930201 | H50: 26563652063200 | I50: OXXO VILA CASCATINHA | J50: Oxxo | K50: Ultrapão Transportes | L50: AV ANTONIO EMMERICK, 67 | M50: Vila Cascatinha, São Vicente - SP | N50: São Vicente | O50: 01.01.0001 | P50: MASSA CONGELADA DE PAO FRANCES RAPIDA - 5KG | Q50: 5 | R50: 0 | S50: PT | T50: 25.09 | U50: 46072.292 | V50: CD Guarulhos Ultrapão (Distribuidora) | W50: 170.95 | X50: 4200 | Y50: Luciano Domenices
A51: 46071.739 | B51: 641513 | C51: 121 - GRU - LITORAL | E51: 46072.773 | F51: SVZ2D07 | G51: 1723030201 | H51: 26563652080300 | I51: OXXO BARTOLOMEU DIAS | J51: Oxxo | K51: Ultrapão Transportes | L51: RUA BARTOLOMEU DIAS, 109, LOTE 21 | M51: Aviação | N51: Praia Grande | O51: 01.01.0001 | P51: MASSA CONGELADA DE PAO FRANCES RAPIDA - 5KG | Q51: 14 | R51: 0 | S51: PT | T51: 86.062 | U51: 46072.292 | V51: CD Guarulhos Ultrapão (Distribuidora) | W51: 877.42 | X51: 4200 | Y51: Luciano Domenices
A52: 46071.739 | B52: 641513 | C52: 121 - GRU - LITORAL | E52: 46072.773 | F52: SVZ2D07 | G52: 1723030201 | H52: 26563652080300 | I52: OXXO BARTOLOMEU DIAS | J52: Oxxo | K52: Ultrapão Transportes | L52: RUA BARTOLOMEU DIAS, 109, LOTE 21 | M52: Aviação | N52: Praia Grande | O52: 01.02.0007 | P52: MASSA CONGELADA DE PAO FRANCES COM GRAOS RAPIDA - 5KG | Q52: 1 | R52: 0 | S52: PT | T52: 86.062 | U52: 46072.292 | V52: CD Guarulhos Ultrapão (Distribuidora) | W52: 877.42 | X52: 4200 | Y52: Luciano Domenices
A53: 46071.739 | B53: 641513 | C53: 121 - GRU - LITORAL | E53: 46072.773 | F53: SVZ2D07 | G53: 1723030201 | H53: 26563652080300 | I53: OXXO BARTOLOMEU DIAS | J53: Oxxo | K53: Ultrapão Transportes | L53: RUA BARTOLOMEU DIAS, 109, LOTE 21 | M53: Aviação | N53: Praia Grande | O53: 01.04.0066 | P53: MASSA CONGELADA DE PÃO DE QUEIJO RECHEADO DE REQUEIJÃO 65G ? CX 10 KG ? 5 UN DE 2 KG | Q53: 1 | R53: 0 | S53: CX | T53: 86.062 | U53: 46072.292 | V53: CD Guarulhos Ultrapão (Distribuidora) | W53: 877.42 | X53: 4200 | Y53: Luciano Domenices
A54: 46071.739 | B54: 641513 | C54: 121 - GRU - LITORAL | E54: 46072.773 | F54: SVZ2D07 | G54: 1723030201 | H54: 26563652080300 | I54: OXXO BARTOLOMEU DIAS | J54: Oxxo | K54: Ultrapão Transportes | L54: RUA BARTOLOMEU DIAS, 109, LOTE 21 | M54: Aviação | N54: Praia Grande | O54: 02.03.0039 | P54: BAGUETE CALABRESA COM CEBOLA CARAMELIZADA 140G | Q54: 1 | R54: 0 | S54: CX | T54: 86.062 | U54: 46072.292 | V54: CD Guarulhos Ultrapão (Distribuidora) | W54: 877.42 | X54: 4200 | Y54: Luciano Domenices
A55: 46071.739 | B55: 641513 | C55: 121 - GRU - LITORAL | E55: 46072.773 | F55: SVZ2D07 | G55: 1725720201 | H55: 26563652080806 | I55: OXXO CAETES | J55: Oxxo | K55: Ultrapão Transportes | L55: Rua Caetés | M55: TUPI | N55: Praia Grande | O55: 01.02.0007 | P55: MASSA CONGELADA DE PAO FRANCES COM GRAOS RAPIDA - 5KG | Q55: 2 | R55: 0 | S55: PT | T55: 20.63 | U55: 46072.292 | V55: CD Guarulhos Ultrapão (Distribuidora) | W55: 359.02 | X55: 4200 | Y55: Luciano Domenices
A56: 46071.739 | B56: 641513 | C56: 121 - GRU - LITORAL | E56: 46072.773 | F56: SVZ2D07 | G56: 1725720201 | H56: 26563652080806 | I56: OXXO CAETES | J56: Oxxo | K56: Ultrapão Transportes | L56: Rua Caetés | M56: TUPI | N56: Praia Grande | O56: 01.04.0066 | P56: MASSA CONGELADA DE PÃO DE QUEIJO RECHEADO DE REQUEIJÃO 65G ? CX 10 KG ? 5 UN DE 2 KG | Q56: 1 | R56: 0 | S56: CX | T56: 20.63 | U56: 46072.292 | V56: CD Guarulhos Ultrapão (Distribuidora) | W56: 359.02 | X56: 4200 | Y56: Luciano Domenices
A57: 46071.739 | B57: 641513 | C57: 121 - GRU - LITORAL | E57: 46072.773 | F57: SVZ2D07 | G57: 1723490201 | H57: 26563652084046 | I57: OXXO OTO MANEIRA | J57: Oxxo | K57: Ultrapão Transportes | L57: RUA A R MANEIRA, 24 | M57: Cidade Ocian | N57: Praia Grande | O57: 01.01.0001 | P57: MASSA CONGELADA DE PAO FRANCES RAPIDA - 5KG | Q57: 10 | R57: 0 | S57: PT | T57: 50.18 | U57: 46072.292 | V57: CD Guarulhos Ultrapão (Distribuidora) | W57: 341.9 | X57: 4200 | Y57: Luciano Domenices
A58: 46071.739 | B58: 641513 | C58: 121 - GRU - LITORAL | E58: 46072.773 | F58: SVZ2D07 | G58: 1723510201 | H58: 26563652066064 | I58: OXXO MONTEIRO DIAS | J58: Oxxo | K58: Ultrapão Transportes | M58: Ocian | N58: Praia Grande | O58: 01.01.0001 | P58: MASSA CONGELADA DE PAO FRANCES RAPIDA - 5KG | Q58: 12 | R58: 0 | S58: PT | T58: 60.216 | U58: 46072.292 | V58: CD Guarulhos Ultrapão (Distribuidora) | W58: 410.28 | X58: 4200 | Y58: Luciano Domenices
A59: 46071.739 | B59: 641513 | C59: 121 - GRU - LITORAL | E59: 46072.773 | F59: SVZ2D07 | G59: 1723570201 | H59: 26563652054058 | I59: OXXO BENEDITO | J59: Oxxo | K59: Ultrapão Transportes | L59: AV DOM PEDRO I, 1009 | M59: Balneário Cidade Atlântica | N59: Guaruja | O59: 01.01.0001 | P59: MASSA CONGELADA DE PAO FRANCES RAPIDA - 5KG | Q59: 11 | R59: 0 | S59: PT | T59: 55.198 | U59: 46072.292 | V59: CD Guarulhos Ultrapão (Distribuidora) | W59: 376.09 | X59: 4200 | Y59: Luciano Domenices
A60: 46071.739 | B60: 641513 | C60: 121 - GRU - LITORAL | E60: 46072.773 | F60: SVZ2D07 | G60: 1723670201 | H60: 26563652052195 | I60: OXXO HERCULANO | J60: Oxxo | K60: Ultrapão Transportes | M60: Boqueirão | N60: Santos | O60: 01.01.0001 | P60: MASSA CONGELADA DE PAO FRANCES RAPIDA - 5KG | Q60: 4 | R60: 0 | S60: PT | T60: 25.072 | U60: 46072.292 | V60: CD Guarulhos Ultrapão (Distribuidora) | W60: 185.77 | X60: 4200 | Y60: Luciano Domenices
A61: 46071.739 | B61: 641513 | C61: 121 - GRU - LITORAL | E61: 46072.773 | F61: SVZ2D07 | G61: 1723670201 | H61: 26563652052195 | I61: OXXO HERCULANO | J61: Oxxo | K61: Ultrapão Transportes | M61: Boqueirão | N61: Santos | O61: 01.02.0007 | P61: MASSA CONGELADA DE PAO FRANCES COM GRAOS RAPIDA - 5KG | Q61: 1 | R61: 0 | S61: PT | T61: 25.072 | U61: 46072.292 | V61: CD Guarulhos Ultrapão (Distribuidora) | W61: 185.77 | X61: 4200 | Y61: Luciano Domenices
A62: 46071.739 | B62: 641513 | C62: 121 - GRU - LITORAL | E62: 46072.773 | F62: SVZ2D07 | G62: 1723730201 | H62: 26563652051628 | I62: OXXO MARLO | J62: Oxxo | K62: Ultrapão Transportes | M62: Mirim | N62: Praia Grande | O62: 01.01.0001 | P62: MASSA CONGELADA DE PAO FRANCES RAPIDA - 5KG | Q62: 11 | R62: 0 | S62: PT | T62: 55.198 | U62: 46072.292 | V62: CD Guarulhos Ultrapão (Distribuidora) | W62: 376.09 | X62: 4200 | Y62: Luciano Domenices
A63: 46071.739 | B63: 641513 | C63: 121 - GRU - LITORAL | E63: 46072.773 | F63: SVZ2D07 | G63: 1723750201 | H63: 26563652052861 | I63: OXXO ITARAREIA | J63: Oxxo | K63: Ultrapão Transportes | M63: Boa Vista | N63: São Vicente | O63: 01.01.0001 | P63: MASSA CONGELADA DE PAO FRANCES RAPIDA - 5KG | Q63: 13 | R63: 0 | S63: PT | T63: 80.864 | U63: 46072.292 | V63: CD Guarulhos Ultrapão (Distribuidora) | W63: 754.48 | X63: 4200 | Y63: Luciano Domenices
A64: 46071.739 | B64: 641513 | C64: 121 - GRU - LITORAL | E64: 46072.773 | F64: SVZ2D07 | G64: 1723750201 | H64: 26563652052861 | I64: OXXO ITARAREIA | J64: Oxxo | K64: Ultrapão Transportes | M64: Boa Vista | N64: São Vicente | O64: 01.02.0007 | P64: MASSA CONGELADA DE PAO FRANCES COM GRAOS RAPIDA - 5KG | Q64: 1 | R64: 0 | S64: PT | T64: 80.864 | U64: 46072.292 | V64: CD Guarulhos Ultrapão (Distribuidora) | W64: 754.48 | X64: 4200 | Y64: Luciano Domenices
A65: 46071.739 | B65: 641513 | C65: 121 - GRU - LITORAL | E65: 46072.773 | F65: SVZ2D07 | G65: 1723750201 | H65: 26563652052861 | I65: OXXO ITARAREIA | J65: Oxxo | K65: Ultrapão Transportes | M65: Boa Vista | N65: São Vicente | O65: 01.04.0066 | P65: MASSA CONGELADA DE PÃO DE QUEIJO RECHEADO DE REQUEIJÃO 65G ? CX 10 KG ? 5 UN DE 2 KG | Q65: 1 | R65: 0 | S65: CX | T65: 80.864 | U65: 46072.292 | V65: CD Guarulhos Ultrapão (Distribuidora) | W65: 754.48 | X65: 4200 | Y65: Luciano Domenices
A66: 46071.739 | B66: 641513 | C66: 121 - GRU - LITORAL | E66: 46072.773 | F66: SVZ2D07 | G66: 1723810201 | H66: 26563652069322 | I66: OXXO MARIA TOGNINI | J66: Oxxo | K66: Ultrapão Transportes | M66: Caiçara | N66: Praia Grande | O66: 01.01.0001 | P66: MASSA CONGELADA DE PAO FRANCES RAPIDA - 5KG | Q66: 12 | R66: 0 | S66: PT | T66: 60.216 | U66: 46072.292 | V66: CD Guarulhos Ultrapão (Distribuidora) | W66: 410.28 | X66: 4200 | Y66: Luciano Domenices
A67: 46071.739 | B67: 641513 | C67: 121 - GRU - LITORAL | E67: 46072.773 | F67: SVZ2D07 | G67: 1724070201 | H67: 26563652080482 | I67: OXXO CAICARINHA | J67: Oxxo | K67: Ultrapão Transportes | L67: AVENIDA NOSSA SENHORA DE FATIMA, 234, LOJA 01 E 02 | M67: Caiçara | N67: Praia Grande | O67: 01.01.0001 | P67: MASSA CONGELADA DE PAO FRANCES RAPIDA - 5KG | Q67: 5 | R67: 0 | S67: PT | T67: 32.06 | U67: 46072.292 | V67: CD Guarulhos Ultrapão (Distribuidora) | W67: 437.35 | X67: 4200 | Y67: Luciano Domenices
A68: 46071.739 | B68: 641513 | C68: 121 - GRU - LITORAL | E68: 46072.773 | F68: SVZ2D07 | G68: 1724070201 | H68: 26563652080482 | I68: OXXO CAICARINHA | J68: Oxxo | K68: Ultrapão Transportes | L68: AVENIDA NOSSA SENHORA DE FATIMA, 234, LOJA 01 E 02 | M68: Caiçara | N68: Praia Grande | O68: 02.01.0004 | P68: PAO DE QUEIJO FORNO DE MINAS ASSADO CONGELADO RECHEADO REQUEIJAO MAX LANCHE | Q68: 1 | R68: 0 | S68: CX | T68: 32.06 | U68: 46072.292 | V68: CD Guarulhos Ultrapão (Distribuidora) | W68: 437.35 | X68: 4200 | Y68: Luciano Domenices
A69: 46071.739 | B69: 641513 | C69: 121 - GRU - LITORAL | E69: 46072.773 | F69: SVZ2D07 | G69: 1724090201 | H69: 26563652058126 | I69: OXXO BRANCO CAST | J69: Oxxo | K69: Ultrapão Transportes | L69: Avenida Presidente Castelo Branco | M69: Guilhermina | N69: Praia Grande | O69: 01.01.0001 | P69: MASSA CONGELADA DE PAO FRANCES RAPIDA - 5KG | Q69: 11 | R69: 0 | S69: PT | T69: 60.198 | U69: 46072.292 | V69: CD Guarulhos Ultrapão (Distribuidora) | W69: 425.1 | X69: 4200 | Y69: Luciano Domenices
A70: 46071.739 | B70: 641513 | C70: 121 - GRU - LITORAL | E70: 46072.773 | F70: SVZ2D07 | G70: 1724090201 | H70: 26563652058126 | I70: OXXO BRANCO CAST | J70: Oxxo | K70: Ultrapão Transportes | L70: Avenida Presidente Castelo Branco | M70: Guilhermina | N70: Praia Grande | O70: 01.02.0007 | P70: MASSA CONGELADA DE PAO FRANCES COM GRAOS RAPIDA - 5KG | Q70: 1 | R70: 0 | S70: PT | T70: 60.198 | U70: 46072.292 | V70: CD Guarulhos Ultrapão (Distribuidora) | W70: 425.1 | X70: 4200 | Y70: Luciano Domenices
A71: 46071.739 | B71: 641513 | C71: 121 - GRU - LITORAL | E71: 46072.773 | F71: SVZ2D07 | G71: 1724110201 | H71: 26563652057901 | I71: OXXO DOURADO MAR | J71: Oxxo | K71: Ultrapão Transportes | M71: Vila Matias | N71: Santos | O71: 01.01.0001 | P71: MASSA CONGELADA DE PAO FRANCES RAPIDA - 5KG | Q71: 3 | R71: 0 | S71: PT | T71: 30.054 | U71: 46072.292 | V71: CD Guarulhos Ultrapão (Distribuidora) | W71: 326.3 | X71: 4200 | Y71: Luciano Domenices
A72: 46071.739 | B72: 641513 | C72: 121 - GRU - LITORAL | E72: 46072.773 | F72: SVZ2D07 | G72: 1724110201 | H72: 26563652057901 | I72: OXXO DOURADO MAR | J72: Oxxo | K72: Ultrapão Transportes | M72: Vila Matias | N72: Santos | O72: 01.02.0007 | P72: MASSA CONGELADA DE PAO FRANCES COM GRAOS RAPIDA - 5KG | Q72: 1 | R72: 0 | S72: PT | T72: 30.054 | U72: 46072.292 | V72: CD Guarulhos Ultrapão (Distribuidora) | W72: 326.3 | X72: 4200 | Y72: Luciano Domenices
A73: 46071.739 | B73: 641513 | C73: 121 - GRU - LITORAL | E73: 46072.773 | F73: SVZ2D07 | G73: 1724110201 | H73: 26563652057901 | I73: OXXO DOURADO MAR | J73: Oxxo | K73: Ultrapão Transportes | M73: Vila Matias | N73: Santos | O73: 01.04.0008 | P73: PAO DE QUEIJO EMPANADO 30G - CX 10KG | Q73: 1 | R73: 0 | S73: CX | T73: 30.054 | U73: 46072.292 | V73: CD Guarulhos Ultrapão (Distribuidora) | W73: 326.3 | X73: 4200 | Y73: Luciano Domenices
A74: 46071.739 | B74: 641513 | C74: 121 - GRU - LITORAL | E74: 46072.773 | F74: SVZ2D07 | G74: 1724130201 | H74: 26563652052608 | I74: OXXO LEOMIL | J74: Oxxo | K74: Ultrapão Transportes | M74: Pitangueiras | N74: Guaruja | O74: 01.01.0001 | P74: MASSA CONGELADA DE PAO FRANCES RAPIDA - 5KG | Q74: 6 | R74: 0 | S74: PT | T74: 30.268 | U74: 46072.292 | V74: CD Guarulhos Ultrapão (Distribuidora) | W74: 354.49 | X74: 4200 | Y74: Luciano Domenices
A75: 46071.739 | B75: 641513 | C75: 121 - GRU - LITORAL | E75: 46072.773 | F75: SVZ2D07 | G75: 1724130201 | H75: 26563652052608 | I75: OXXO LEOMIL | J75: Oxxo | K75: Ultrapão Transportes | M75: Pitangueiras | N75: Guaruja | O75: 02.02.0029 | P75: RISOLES LAMINADO FRITO DE FRANGO 150G | Q75: 1 | R75: 0 | S75: CX | T75: 30.268 | U75: 46072.292 | V75: CD Guarulhos Ultrapão (Distribuidora) | W75: 354.49 | X75: 4200 | Y75: Luciano Domenices
A76: 46071.739 | B76: 641513 | C76: 121 - GRU - LITORAL | E76: 46072.773 | F76: SVZ2D07 | G76: 1724170201 | H76: 26563652052276 | I76: OXXO CANTO DO FORTE | J76: Oxxo | K76: Ultrapão Transportes | L76: Rua General Otelo Rodrigues Franco | M76: Canto Do Forte | N76: Praia Grande | O76: 01.01.0001 | P76: MASSA CONGELADA DE PAO FRANCES RAPIDA - 5KG | Q76: 4 | R76: 0 | S76: PT | T76: 40.072 | U76: 46072.292 | V76: CD Guarulhos Ultrapão (Distribuidora) | W76: 409.5 | X76: 4200 | Y76: Luciano Domenices
A77: 46071.739 | B77: 641513 | C77: 121 - GRU - LITORAL | E77: 46072.773 | F77: SVZ2D07 | G77: 1724170201 | H77: 26563652052276 | I77: OXXO CANTO DO FORTE | J77: Oxxo | K77: Ultrapão Transportes | L77: Rua General Otelo Rodrigues Franco | M77: Canto Do Forte | N77: Praia Grande | O77: 01.02.0007 | P77: MASSA CONGELADA DE PAO FRANCES COM GRAOS RAPIDA - 5KG | Q77: 2 | R77: 0 | S77: PT | T77: 40.072 | U77: 46072.292 | V77: CD Guarulhos Ultrapão (Distribuidora) | W77: 409.5 | X77: 4200 | Y77: Luciano Domenices
A78: 46071.739 | B78: 641513 | C78: 121 - GRU - LITORAL | E78: 46072.773 | F78: SVZ2D07 | G78: 1724170201 | H78: 26563652052276 | I78: OXXO CANTO DO FORTE | J78: Oxxo | K78: Ultrapão Transportes | L78: Rua General Otelo Rodrigues Franco | M78: Canto Do Forte | N78: Praia Grande | O78: 01.04.0008 | P78: PAO DE QUEIJO EMPANADO 30G - CX 10KG | Q78: 1 | R78: 0 | S78: CX | T78: 40.072 | U78: 46072.292 | V78: CD Guarulhos Ultrapão (Distribuidora) | W78: 409.5 | X78: 4200 | Y78: Luciano Domenices
A79: 46071.739 | B79: 641513 | C79: 121 - GRU - LITORAL | E79: 46072.773 | F79: SVZ2D07 | G79: 1724190201 | H79: 26563652069837 | I79: OXXO GOMESAMADO | J79: Oxxo | K79: Ultrapão Transportes | M79: Vila Assuncao | N79: Praia Grande | O79: 01.01.0001 | P79: MASSA CONGELADA DE PAO FRANCES RAPIDA - 5KG | Q79: 13 | R79: 0 | S79: PT | T79: 65.234 | U79: 46072.292 | V79: CD Guarulhos Ultrapão (Distribuidora) | W79: 444.47 | X79: 4200 | Y79: Luciano Domenices
A80: 46071.739 | B80: 641513 | C80: 121 - GRU - LITORAL | E80: 46072.773 | F80: SVZ2D07 | G80: 1724570201 | H80: 26563652065335 | I80: OXXO GENERAL CAMARA | J80: Oxxo | K80: Ultrapão Transportes | L80: Rua Augusto Severo | M80: CENTRO | N80: Santos | O80: 01.02.0007 | P80: MASSA CONGELADA DE PAO FRANCES COM GRAOS RAPIDA - 5KG | Q80: 1 | R80: 0 | S80: PT | T80: 5.16 | U80: 46072.292 | V80: CD Guarulhos Ultrapão (Distribuidora) | W80: 198.36 | X80: 4200 | Y80: Luciano Domenices
A81: 46071.739 | B81: 641513 | C81: 121 - GRU - LITORAL | E81: 46072.773 | F81: SVZ2D07 | G81: 1724570201 | H81: 26563652065335 | I81: OXXO GENERAL CAMARA | J81: Oxxo | K81: Ultrapão Transportes | L81: Rua Augusto Severo | M81: CENTRO | N81: Santos | O81: 02.02.0029 | P81: RISOLES LAMINADO FRITO DE FRANGO 150G | Q81: 1 | R81: 0 | S81: CX | T81: 5.16 | U81: 46072.292 | V81: CD Guarulhos Ultrapão (Distribuidora) | W81: 198.36 | X81: 4200 | Y81: Luciano Domenices
A82: 46071.739 | B82: 641514 | C82: 65 - GRU - SÃO BERNARDO | E82: 46072.773 | F82: SXN4A56 | G82: 1708810201 | H82: 2001242000125 | I82: AUTO POSTO SANTO ANDRE | J82: Varejo | K82: Ultrapão Transportes | L82: AVENIDA ANDRADE NEVES, 159 | M82: VILA ALZIRA | N82: Santo André | O82: 01.01.0001 | P82: MASSA CONGELADA DE PAO FRANCES RAPIDA - 5KG | Q82: 2 | R82: 0 | S82: PT | T82: 80.036 | U82: 46072.292 | V82: CD Guarulhos Ultrapão (Distribuidora) | W82: 519.74 | X82: 4200 | Y82: Djalma Santino da silva
A83: 46071.739 | B83: 641514 | C83: 65 - GRU - SÃO BERNARDO | E83: 46072.773 | F83: SXN4A56 | G83: 1708810201 | H83: 2001242000125 | I83: AUTO POSTO SANTO ANDRE | J83: Varejo | K83: Ultrapão Transportes | L83: AVENIDA ANDRADE NEVES, 159 | M83: VILA ALZIRA | N83: Santo André | O83: 01.01.0002 | P83: MASSA CONGELADA DE PAO FRANCES MEDIA - 5KG | Q83: 14 | R83: 0 | S83: PT | T83: 80.036 | U83: 46072.292 | V83: CD Guarulhos Ultrapão (Distribuidora) | W83: 519.74 | X83: 4200 | Y83: Djalma Santino da silva
A84: 46071.739 | B84: 641514 | C84: 65 - GRU - SÃO BERNARDO | E84: 46072.773 | F84: SXN4A56 | G84: 1716010201 | H84: 9000493000487 | I84: ST MARCHE SAO CAETANO | J84: ST Marche | K84: Ultrapão Transportes | L84: AL TERRACOTA, 545 | M84: CERAMICA | N84: São Caetano do Sul | O84: 01.04.0021 | P84: MASSA CONGELADA DE PÃO DE QUEIJO RECHEADO DE GOIABADA 65G - 2KG | Q84: 20 | R84: 0 | S84: PT | T84: 425.2 | U84: 46072.292 | V84: CD Guarulhos Ultrapão (Distribuidora) | W84: 2696.4 | X84: 4200 | Y84: Djalma Santino da silva
A85: 46071.739 | B85: 641514 | C85: 65 - GRU - SÃO BERNARDO | E85: 46072.773 | F85: SXN4A56 | G85: 1716010201 | H85: 9000493000487 | I85: ST MARCHE SAO CAETANO | J85: ST Marche | K85: Ultrapão Transportes | L85: AL TERRACOTA, 545 | M85: CERAMICA | N85: São Caetano do Sul | O85: 01.04.0022 | P85: MASSA CONGELADA DE PÃO DE QUEIJO RECHEADO DE REQUEIJÃO 65G - 2KG | Q85: 20 | R85: 0 | S85: PT | T85: 425.2 | U85: 46072.292 | V85: CD Guarulhos Ultrapão (Distribuidora) | W85: 2696.4 | X85: 4200 | Y85: Djalma Santino da silva
A86: 46071.739 | B86: 641514 | C86: 65 - GRU - SÃO BERNARDO | E86: 46072.773 | F86: SXN4A56 | G86: 1722010201 | H86: 62353476001569 | I86: RZ GESTAO JAU | J86: Shell Select | K86: Ultrapão Transportes | L86: RUA JOAQUIM NABUCO, 506, CONJ B | M86: CENTRO | N86: São Bernardo do Campo | O86: 02.01.0004 | P86: PAO DE QUEIJO FORNO DE MINAS ASSADO CONGELADO RECHEADO REQUEIJAO MAX LANCHE | Q86: 2 | R86: 0 | S86: CX | T86: 28.36 | U86: 46072.292 | V86: CD Guarulhos Ultrapão (Distribuidora) | W86: 1041.3 | X86: 4200 | Y86: Djalma Santino da silva
A87: 46071.739 | B87: 641514 | C87: 65 - GRU - SÃO BERNARDO | E87: 46072.773 | F87: SXN4A56 | G87: 1722010201 | H87: 62353476001569 | I87: RZ GESTAO JAU | J87: Shell Select | K87: Ultrapão Transportes | L87: RUA JOAQUIM NABUCO, 506, CONJ B | M87: CENTRO | N87: São Bernardo do Campo | O87: 02.01.0005 | P87: PAO DE QUEIJO FORNO DE MINAS ASSADO CONGELADO MAX LANCHE | Q87: 2 | R87: 0 | S87: CX | T87: 28.36 | U87: 46072.292 | V87: CD Guarulhos Ultrapão (Distribuidora) | W87: 1041.3 | X87: 4200 | Y87: Djalma Santino da silva
A88: 46071.739 | B88: 641514 | C88: 65 - GRU - SÃO BERNARDO | E88: 46072.773 | F88: SXN4A56 | G88: 1722070201 | H88: 62353476002026 | I88: RZ GESTAO ESTONIA 3 | J88: Shell Select | K88: Ultrapão Transportes | L88: RUA SANTA FILOMENA, 751, CONJ B | M88: CENTRO | N88: São Bernardo do Campo | O88: 02.01.0004 | P88: PAO DE QUEIJO FORNO DE MINAS ASSADO CONGELADO RECHEADO REQUEIJAO MAX LANCHE | Q88: 2 | R88: 0 | S88: CX | T88: 13.94 | U88: 46072.292 | V88: CD Guarulhos Ultrapão (Distribuidora) | W88: 532.8 | X88: 4200 | Y88: Djalma Santino da silva
A89: 46071.739 | B89: 641514 | C89: 65 - GRU - SÃO BERNARDO | E89: 46072.773 | F89: SXN4A56 | G89: 1722110201 | H89: 62353476002026 | I89: RZ GESTAO ESTONIA 3 | J89: Shell Select | K89: Ultrapão Transportes | L89: RUA SANTA FILOMENA, 751, CONJ B | M89: CENTRO | N89: São Bernardo do Campo | O89: 02.01.0005 | P89: PAO DE QUEIJO FORNO DE MINAS ASSADO CONGELADO MAX LANCHE | Q89: 2 | R89: 0 | S89: CX | T89: 14.42 | U89: 46072.292 | V89: CD Guarulhos Ultrapão (Distribuidora) | W89: 508.5 | X89: 4200 | Y89: Djalma Santino da silva
A90: 46071.739 | B90: 641514 | C90: 65 - GRU - SÃO BERNARDO | E90: 46072.773 | F90: SXN4A56 | G90: 1722150201 | H90: 62353476002026 | I90: RZ GESTAO ESTONIA 3 | J90: Shell Select | K90: Ultrapão Transportes | L90: RUA SANTA FILOMENA, 751, CONJ B | M90: CENTRO | N90: São Bernardo do Campo | O90: 01.04.0008 | P90: PAO DE QUEIJO EMPANADO 30G - CX 10KG | Q90: 3 | R90: 0 | S90: CX | T90: 30 | U90: 46072.292 | V90: CD Guarulhos Ultrapão (Distribuidora) | W90: 524.16 | X90: 4200 | Y90: Djalma Santino da silva
A91: 46071.739 | B91: 641514 | C91: 65 - GRU - SÃO BERNARDO | E91: 46072.773 | F91: SXN4A56 | G91: 1722190201 | H91: 62353476002026 | I91: RZ GESTAO ESTONIA 3 | J91: Shell Select | K91: Ultrapão Transportes | L91: RUA SANTA FILOMENA, 751, CONJ B | M91: CENTRO | N91: São Bernardo do Campo | O91: 01.02.0007 | P91: MASSA CONGELADA DE PAO FRANCES COM GRAOS RAPIDA - 5KG | Q91: 3 | R91: 0 | S91: PT | T91: 15 | U91: 46072.292 | V91: CD Guarulhos Ultrapão (Distribuidora) | W91: 147.03 | X91: 4200 | Y91: Djalma Santino da silva
A92: 46071.739 | B92: 641514 | C92: 65 - GRU - SÃO BERNARDO | E92: 46072.773 | F92: SXN4A56 | G92: 1722290201 | H92: 62353476002026 | I92: RZ GESTAO ESTONIA 3 | J92: Shell Select | K92: Ultrapão Transportes | L92: RUA SANTA FILOMENA, 751, CONJ B | M92: CENTRO | N92: São Bernardo do Campo | O92: 01.01.0001 | P92: MASSA CONGELADA DE PAO FRANCES RAPIDA - 5KG | Q92: 8 | R92: 0 | S92: PT | T92: 40.144 | U92: 46072.292 | V92: CD Guarulhos Ultrapão (Distribuidora) | W92: 273.52 | X92: 4200 | Y92: Djalma Santino da silva
A93: 46071.739 | B93: 641514 | C93: 65 - GRU - SÃO BERNARDO | E93: 46072.773 | F93: SXN4A56 | G93: 1725740201 | H93: 26563652027328 | I93: OXXO PAIXÃO GUIDO | J93: Oxxo | K93: Ultrapão Transportes | M93: Mauá | N93: São Caetano do Sul | O93: 01.01.0001 | P93: MASSA CONGELADA DE PAO FRANCES RAPIDA - 5KG | Q93: 11 | R93: 0 | S93: PT | T93: 58.398 | U93: 46072.292 | V93: CD Guarulhos Ultrapão (Distribuidora) | W93: 442.09 | X93: 4200 | Y93: Djalma Santino da silva
A94: 46071.739 | B94: 641514 | C94: 65 - GRU - SÃO BERNARDO | E94: 46072.773 | F94: SXN4A56 | G94: 1725740201 | H94: 26563652027328 | I94: OXXO PAIXÃO GUIDO | J94: Oxxo | K94: Ultrapão Transportes | M94: Mauá | N94: São Caetano do Sul | O94: 01.10.0013 | P94: MINI BAGUETE FRANCESA LEVIASSA - PT 0,240 KG - CX 2,88 KG - 12 UN | Q94: 1 | R94: 0 | S94: CX | T94: 58.398 | U94: 46072.292 | V94: CD Guarulhos Ultrapão (Distribuidora) | W94: 442.09 | X94: 4200 | Y94: Djalma Santino da silva
A95: 46071.739 | B95: 641514 | C95: 65 - GRU - SÃO BERNARDO | E95: 46072.773 | F95: SXN4A56 | G95: 1725820201 | H95: 26563652057073 | I95: OXXO FLOR DOS VIANAS | J95: Oxxo | K95: Ultrapão Transportes | M95: Baeta Neves | N95: São Bernardo do Campo | O95: 01.01.0001 | P95: MASSA CONGELADA DE PAO FRANCES RAPIDA - 5KG | Q95: 12 | R95: 0 | S95: PT | T95: 60.216 | U95: 46072.292 | V95: CD Guarulhos Ultrapão (Distribuidora) | W95: 410.28 | X95: 4200 | Y95: Djalma Santino da silva
A96: 46071.739 | B96: 641514 | C96: 65 - GRU - SÃO BERNARDO | E96: 46072.773 | F96: SXN4A56 | G96: 1725880201 | H96: 26563652045229 | I96: OXXO AQUATICA | J96: Oxxo | K96: Ultrapão Transportes | L96: R BRASILIO MACHADO, 238 | M96: Centro | N96: São Bernardo do Campo | O96: 01.01.0001 | P96: MASSA CONGELADA DE PAO FRANCES RAPIDA - 5KG | Q96: 11 | R96: 0 | S96: PT | T96: 60.198 | U96: 46072.292 | V96: CD Guarulhos Ultrapão (Distribuidora) | W96: 425.1 | X96: 4200 | Y96: Djalma Santino da silva
A97: 46071.739 | B97: 641514 | C97: 65 - GRU - SÃO BERNARDO | E97: 46072.773 | F97: SXN4A56 | G97: 1725880201 | H97: 26563652045229 | I97: OXXO AQUATICA | J97: Oxxo | K97: Ultrapão Transportes | L97: R BRASILIO MACHADO, 238 | M97: Centro | N97: São Bernardo do Campo | O97: 01.02.0007 | P97: MASSA CONGELADA DE PAO FRANCES COM GRAOS RAPIDA - 5KG | Q97: 1 | R97: 0 | S97: PT | T97: 60.198 | U97: 46072.292 | V97: CD Guarulhos Ultrapão (Distribuidora) | W97: 425.1 | X97: 4200 | Y97: Djalma Santino da silva
A98: 46071.739 | B98: 641514 | C98: 65 - GRU - SÃO BERNARDO | E98: 46072.773 | F98: SXN4A56 | G98: 1726000201 | H98: 26563652024817 | I98: OXXO SENADOR VERGUEIRO | J98: Oxxo | K98: Ultrapão Transportes | M98: Rudge Ramos | N98: São Bernardo do Campo | O98: 01.01.0001 | P98: MASSA CONGELADA DE PAO FRANCES RAPIDA - 5KG | Q98: 9 | R98: 0 | S98: PT | T98: 50.162 | U98: 46072.292 | V98: CD Guarulhos Ultrapão (Distribuidora) | W98: 356.72 | X98: 4200 | Y98: Djalma Santino da silva
A99: 46071.739 | B99: 641514 | C99: 65 - GRU - SÃO BERNARDO | E99: 46072.773 | F99: SXN4A56 | G99: 1726000201 | H99: 26563652024817 | I99: OXXO SENADOR VERGUEIRO | J99: Oxxo | K99: Ultrapão Transportes | M99: Rudge Ramos | N99: São Bernardo do Campo | O99: 01.02.0007 | P99: MASSA CONGELADA DE PAO FRANCES COM GRAOS RAPIDA - 5KG | Q99: 1 | R99: 0 | S99: PT | T99: 50.162 | U99: 46072.292 | V99: CD Guarulhos Ultrapão (Distribuidora) | W99: 356.72 | X99: 4200 | Y99: Djalma Santino da silva
A100: 46071.739 | B100: 641514 | C100: 65 - GRU - SÃO BERNARDO | E100: 46072.773 | F100: SXN4A56 | G100: 1726230201 | H100: 26563652031511 | I100: OXXO ABRAO SALOTTI | J100: Oxxo | K100: Ultrapão Transportes | L100: R AFONSINA, 506 | M100: Rudge Ramos | N100: São Bernardo do Campo | O100: 01.01.0001 | P100: MASSA CONGELADA DE PAO FRANCES RAPIDA - 5KG | Q100: 6 | R100: 0 | S100: PT | T100: 30.108 | U100: 46072.292 | V100: CD Guarulhos Ultrapão (Distribuidora) | W100: 205.14 | X100: 4200 | Y100: Djalma Santino da silva
...

Sheet TODAS AS PLACAS
A1: FROTA | B1: PLACA: | C1: CAPACIDADE: | D1: TIPO: | E1: Rodízio
A2: PROPRIA | B2: SWY3E25 | C2: 4200 | D2: 46115 | E2: Quarta-feira
A3: PROPRIA | B3: EZO8E62 | C3: 4200 | D3: 46115 | E3: Segunda-feira
A4: PROPRIA | B4: FED2A32 | C4: 4200 | D4: 46115 | E4: Segunda-feira
A5: PROPRIA | B5: STS8F92 | C5: 4200 | D5: 46115 | E5: Segunda-feira
A6: PROPRIA | B6: SVZ2D07 | C6: 4200 | D6: 46115 | E6: Quinta-feira
A7: PROPRIA | B7: SSV3J72 | C7: 4200 | D7: 46115 | E7: Segunda-feira
A8: PROPRIA | B8: ENI7G21 | C8: 4200 | D8: 46115 | E8: Segunda-feira
A9: PROPRIA | B9: SWB3F77 | C9: 4200 | D9: 46115 | E9: Quinta-feira
A10: PROPRIA | B10: SVZ3G77 | C10: 4200 | D10: 46115 | E10: Quinta-feira
A11: PROPRIA | B11: SWI6E54 | C11: 4200 | D11: 46115 | E11: Terça-feira
A12: PROPRIA | B12: EOF7G31 | C12: 4200 | D12: 46115 | E12: Segunda-feira
A13: PROPRIA | B13: SXN4A56 | C13: 4500/ 3 Palet | D13: 46115 | E13: Quarta-feira
A14: PROPRIA | B14: SXN5F36 | C14: 4500/ 8 Palet | D14: 46115 | E14: Quarta-feira
A15: PROPRIA | B15: SXM5I76 | C15: 4500/ 8 Palet | D15: 46115 | E15: Quarta-feira
A16: PROPRIA | B16: RFS3I44 | C16: 1500 / 2 Palet | D16: 46115 | E16: Terça-feira
A17: PROPRIA | B17: SEG0001 | D17: 46115 | E17: Segunda-feira
A18: PROPRIA | B18: SEG0002 | D18: 46115 | E18: Segunda-feira
A19: PROPRIA | B19: IXM3E88 | C19: 8000 | D19: TRUCK | E19: Sexta-feira
A20: AGREGADO | B20: FSS4C66 | C20: 2700 | D20: 46115 | E20: Quarta-feira
A21: AGREGADO | B21: FUO2I21 | C21: 2700 | D21: 46115 | E21: Segunda-feira
A22: AGREGADO | B22: FTF2H12 | C22: 2500 | D22: 46115 | E22: Segunda-feira
A23: AGREGADO | B23: SVA5J31 | C23: 2500 | D23: 46115 | E23: Segunda-feira
A24: TERCEIRO | B24: EWJ3E57 | C24: 2500 | D24: VUC | E24: Quinta-feira
A25: TERCEIRO | B25: ELQ2549 | C25: 2500 | D25: VUC | E25: Sexta-feira
A26: TERCEIRO | B26: EMU1F41 | C26: 2500 | D26: VUC | E26: Segunda-feira
A27: TERCEIRO | B27: DTD1C82 | C27: 1500 | D27: VAN | E27: Segunda-feira
A28: TERCEIRO | B28: FBV9B83 | C28: 700 | D28: FIORINO | E28: Terça-feira
A29: TERCEIRO | B29: EFW3195 | C29: 1500 | D29: HR | E29: Quarta-feira
A30: TERCEIRO | B30: FSS4C65 | C30: 1500 | D30: HR | E30: Quarta-feira
A31: TERCEIRO | B31: HBN8E36 | C31: 1500 | D31: HR | E31: Quarta-feira
A32: TERCEIRO | B32: FUO8F70 | C32: 500 | D32: FIORINO | E32: Sexta-feira
A33: TERCEIRO | B33: EUG6C39 | C33: 1500 | D33: HR | E33: Sexta-feira
A34: TERCEIRO | B34: FQQ1H88 | C34: 500 | D34: FIORINO | E34: Quinta-feira
A35: TERCEIRO | B35: ONL6155 | C35: 1500 | D35: HR | E35: Quarta-feira
... A38: TERCEIRO | B38: RTV5C90 | C38: 500 | D38: FIORINO | E38: Sexta-feira
A39: PROPRIA | B39: GAF9F72 | C39: 4500/ 8 Palet | D39: 46115 | E39: Segunda-feira

Sheet DIVERGÊNCIAS
A1: CÓDIGO DE BARRAS | B1: PRODUTO | C1: QUANTIDADE BIPADA | D1: QUANTIDADE ROMANEIO | E1: DIFERENÇA | F1: TIPO
A2: =IFERROR(_xlfn.SINGLE(INDEX('ROMANEIO POR ITEM'!#REF!, SMALL(IF(_xlfn.SINGLE('ROMANEIO POR ITEM'!#REF!)<>0,_xlfn.SINGLE( ROW('ROMANEIO POR ITEM'!#REF!))-ROW('ROMANEIO POR ITEM'!#REF!)+1), ROW(A1)))), "") | B2: =IF(A2="", "", VLOOKUP(A2, 'ROMANEIO POR ITEM'!#REF!, 2, FALSE)) | C2: =IF(A2="", "", VLOOKUP(A2, 'ROMANEIO POR ITEM'!#REF!, 3, FALSE)) | D2: =IF(A2="", "", VLOOKUP(A2, 'ROMANEIO POR ITEM'!#REF!, 4, FALSE)) | E2: =IF(A2="", "", VLOOKUP(A2, 'ROMANEIO POR ITEM'!#REF!, 5, FALSE)) | F2: =IF(A2="", "", VLOOKUP(A2, 'ROMANEIO POR ITEM'!#REF!, 6, FALSE))
A3: =IFERROR(_xlfn.SINGLE(INDEX('ROMANEIO POR ITEM'!#REF!, SMALL(IF(_xlfn.SINGLE('ROMANEIO POR ITEM'!#REF!)<>0,_xlfn.SINGLE( ROW('ROMANEIO POR ITEM'!#REF!))-ROW('ROMANEIO POR ITEM'!#REF!)+1), ROW(A2)))), "") | B3: =IF(A3="", "", VLOOKUP(A3, 'ROMANEIO POR ITEM'!#REF!, 2, FALSE)) | C3: =IF(A3="", "", VLOOKUP(A3, 'ROMANEIO POR ITEM'!#REF!, 3, FALSE)) | D3: =IF(A3="", "", VLOOKUP(A3, 'ROMANEIO POR ITEM'!#REF!, 4, FALSE)) | E3: =IF(A3="", "", VLOOKUP(A3, 'ROMANEIO POR ITEM'!#REF!, 5, FALSE)) | F3: =IF(A3="", "", VLOOKUP(A3, 'ROMANEIO POR ITEM'!#REF!, 6, FALSE))
A4: =IFERROR(_xlfn.SINGLE(INDEX('ROMANEIO POR ITEM'!#REF!, SMALL(IF(_xlfn.SINGLE('ROMANEIO POR ITEM'!#REF!)<>0,_xlfn.SINGLE( ROW('ROMANEIO POR ITEM'!#REF!))-ROW('ROMANEIO POR ITEM'!#REF!)+1), ROW(A3)))), "") | B4: =IF(A4="", "", VLOOKUP(A4, 'ROMANEIO POR ITEM'!#REF!, 2, FALSE)) | C4: =IF(A4="", "", VLOOKUP(A4, 'ROMANEIO POR ITEM'!#REF!, 3, FALSE)) | D4: =IF(A4="", "", VLOOKUP(A4, 'ROMANEIO POR ITEM'!#REF!, 4, FALSE)) | E4: =IF(A4="", "", VLOOKUP(A4, 'ROMANEIO POR ITEM'!#REF!, 5, FALSE)) | F4: =IF(A4="", "", VLOOKUP(A4, 'ROMANEIO POR ITEM'!#REF!, 6, FALSE))
A5: =IFERROR(_xlfn.SINGLE(INDEX('ROMANEIO POR ITEM'!#REF!, SMALL(IF(_xlfn.SINGLE('ROMANEIO POR ITEM'!#REF!)<>0,_xlfn.SINGLE( ROW('ROMANEIO POR ITEM'!#REF!))-ROW('ROMANEIO POR ITEM'!#REF!)+1), ROW(A4)))), "") | B5: =IF(A5="", "", VLOOKUP(A5, 'ROMANEIO POR ITEM'!#REF!, 2, FALSE)) | C5: =IF(A5="", "", VLOOKUP(A5, 'ROMANEIO POR ITEM'!#REF!, 3, FALSE)) | D5: =IF(A5="", "", VLOOKUP(A5, 'ROMANEIO POR ITEM'!#REF!, 4, FALSE)) | E5: =IF(A5="", "", VLOOKUP(A5, 'ROMANEIO POR ITEM'!#REF!, 5, FALSE)) | F5: =IF(A5="", "", VLOOKUP(A5, 'ROMANEIO POR ITEM'!#REF!, 6, FALSE))
A6: =IFERROR(_xlfn.SINGLE(INDEX('ROMANEIO POR ITEM'!#REF!, SMALL(IF(_xlfn.SINGLE('ROMANEIO POR ITEM'!#REF!)<>0,_xlfn.SINGLE( ROW('ROMANEIO POR ITEM'!#REF!))-ROW('ROMANEIO POR ITEM'!#REF!)+1), ROW(A5)))), "") | B6: =IF(A6="", "", VLOOKUP(A6, 'ROMANEIO POR ITEM'!#REF!, 2, FALSE)) | C6: =IF(A6="", "", VLOOKUP(A6, 'ROMANEIO POR ITEM'!#REF!, 3, FALSE)) | D6: =IF(A6="", "", VLOOKUP(A6, 'ROMANEIO POR ITEM'!#REF!, 4, FALSE)) | E6: =IF(A6="", "", VLOOKUP(A6, 'ROMANEIO POR ITEM'!#REF!, 5, FALSE)) | F6: =IF(A6="", "", VLOOKUP(A6, 'ROMANEIO POR ITEM'!#REF!, 6, FALSE))
A7: =IFERROR(_xlfn.SINGLE(INDEX('ROMANEIO POR ITEM'!#REF!, SMALL(IF(_xlfn.SINGLE('ROMANEIO POR ITEM'!#REF!)<>0,_xlfn.SINGLE( ROW('ROMANEIO POR ITEM'!#REF!))-ROW('ROMANEIO POR ITEM'!#REF!)+1), ROW(A6)))), "") | B7: =IF(A7="", "", VLOOKUP(A7, 'ROMANEIO POR ITEM'!#REF!, 2, FALSE)) | C7: =IF(A7="", "", VLOOKUP(A7, 'ROMANEIO POR ITEM'!#REF!, 3, FALSE)) | D7: =IF(A7="", "", VLOOKUP(A7, 'ROMANEIO POR ITEM'!#REF!, 4, FALSE)) | E7: =IF(A7="", "", VLOOKUP(A7, 'ROMANEIO POR ITEM'!#REF!, 5, FALSE)) | F7: =IF(A7="", "", VLOOKUP(A7, 'ROMANEIO POR ITEM'!#REF!, 6, FALSE))
A8: =IFERROR(_xlfn.SINGLE(INDEX('ROMANEIO POR ITEM'!#REF!, SMALL(IF(_xlfn.SINGLE('ROMANEIO POR ITEM'!#REF!)<>0,_xlfn.SINGLE( ROW('ROMANEIO POR ITEM'!#REF!))-ROW('ROMANEIO POR ITEM'!#REF!)+1), ROW(A7)))), "") | B8: =IF(A8="", "", VLOOKUP(A8, 'ROMANEIO POR ITEM'!#REF!, 2, FALSE)) | C8: =IF(A8="", "", VLOOKUP(A8, 'ROMANEIO POR ITEM'!#REF!, 3, FALSE)) | D8: =IF(A8="", "", VLOOKUP(A8, 'ROMANEIO POR ITEM'!#REF!, 4, FALSE)) | E8: =IF(A8="", "", VLOOKUP(A8, 'ROMANEIO POR ITEM'!#REF!, 5, FALSE)) | F8: =IF(A8="", "", VLOOKUP(A8, 'ROMANEIO POR ITEM'!#REF!, 6, FALSE))
A9: =IFERROR(_xlfn.SINGLE(INDEX('ROMANEIO POR ITEM'!#REF!, SMALL(IF(_xlfn.SINGLE('ROMANEIO POR ITEM'!#REF!)<>0,_xlfn.SINGLE( ROW('ROMANEIO POR ITEM'!#REF!))-ROW('ROMANEIO POR ITEM'!#REF!)+1), ROW(A8)))), "") | B9: =IF(A9="", "", VLOOKUP(A9, 'ROMANEIO POR ITEM'!#REF!, 2, FALSE)) | C9: =IF(A9="", "", VLOOKUP(A9, 'ROMANEIO POR ITEM'!#REF!, 3, FALSE)) | D9: =IF(A9="", "", VLOOKUP(A9, 'ROMANEIO POR ITEM'!#REF!, 4, FALSE)) | E9: =IF(A9="", "", VLOOKUP(A9, 'ROMANEIO POR ITEM'!#REF!, 5, FALSE)) | F9: =IF(A9="", "", VLOOKUP(A9, 'ROMANEIO POR ITEM'!#REF!, 6, FALSE))
A10: =IFERROR(_xlfn.SINGLE(INDEX('ROMANEIO POR ITEM'!#REF!, SMALL(IF(_xlfn.SINGLE('ROMANEIO POR ITEM'!#REF!)<>0,_xlfn.SINGLE( ROW('ROMANEIO POR ITEM'!#REF!))-ROW('ROMANEIO POR ITEM'!#REF!)+1), ROW(A9)))), "") | B10: =IF(A10="", "", VLOOKUP(A10, 'ROMANEIO POR ITEM'!#REF!, 2, FALSE)) | C10: =IF(A10="", "", VLOOKUP(A10, 'ROMANEIO POR ITEM'!#REF!, 3, FALSE)) | D10: =IF(A10="", "", VLOOKUP(A10, 'ROMANEIO POR ITEM'!#REF!, 4, FALSE)) | E10: =IF(A10="", "", VLOOKUP(A10, 'ROMANEIO POR ITEM'!#REF!, 5, FALSE)) | F10: =IF(A10="", "", VLOOKUP(A10, 'ROMANEIO POR ITEM'!#REF!, 6, FALSE))
A11: =IFERROR(_xlfn.SINGLE(INDEX('ROMANEIO POR ITEM'!#REF!, SMALL(IF(_xlfn.SINGLE('ROMANEIO POR ITEM'!#REF!)<>0,_xlfn.SINGLE( ROW('ROMANEIO POR ITEM'!#REF!))-ROW('ROMANEIO POR ITEM'!#REF!)+1), ROW(A10)))), "") | B11: =IF(A11="", "", VLOOKUP(A11, 'ROMANEIO POR ITEM'!#REF!, 2, FALSE)) | C11: =IF(A11="", "", VLOOKUP(A11, 'ROMANEIO POR ITEM'!#REF!, 3, FALSE)) | D11: =IF(A11="", "", VLOOKUP(A11, 'ROMANEIO POR ITEM'!#REF!, 4, FALSE)) | E11: =IF(A11="", "", VLOOKUP(A11, 'ROMANEIO POR ITEM'!#REF!, 5, FALSE)) | F11: =IF(A11="", "", VLOOKUP(A11, 'ROMANEIO POR ITEM'!#REF!, 6, FALSE))
A12: =IFERROR(_xlfn.SINGLE(INDEX('ROMANEIO POR ITEM'!#REF!, SMALL(IF(_xlfn.SINGLE('ROMANEIO POR ITEM'!#REF!)<>0,_xlfn.SINGLE( ROW('ROMANEIO POR ITEM'!#REF!))-ROW('ROMANEIO POR ITEM'!#REF!)+1), ROW(A11)))), "") | B12: =IF(A12="", "", VLOOKUP(A12, 'ROMANEIO POR ITEM'!#REF!, 2, FALSE)) | C12: =IF(A12="", "", VLOOKUP(A12, 'ROMANEIO POR ITEM'!#REF!, 3, FALSE)) | D12: =IF(A12="", "", VLOOKUP(A12, 'ROMANEIO POR ITEM'!#REF!, 4, FALSE)) | E12: =IF(A12="", "", VLOOKUP(A12, 'ROMANEIO POR ITEM'!#REF!, 5, FALSE)) | F12: =IF(A12="", "", VLOOKUP(A12, 'ROMANEIO POR ITEM'!#REF!, 6, FALSE))
A13: =IFERROR(_xlfn.SINGLE(INDEX('ROMANEIO POR ITEM'!#REF!, SMALL(IF(_xlfn.SINGLE('ROMANEIO POR ITEM'!#REF!)<>0,_xlfn.SINGLE( ROW('ROMANEIO POR ITEM'!#REF!))-ROW('ROMANEIO POR ITEM'!#REF!)+1), ROW(A12)))), "") | B13: =IF(A13="", "", VLOOKUP(A13, 'ROMANEIO POR ITEM'!#REF!, 2, FALSE)) | C13: =IF(A13="", "", VLOOKUP(A13, 'ROMANEIO POR ITEM'!#REF!, 3, FALSE)) | D13: =IF(A13="", "", VLOOKUP(A13, 'ROMANEIO POR ITEM'!#REF!, 4, FALSE)) | E13: =IF(A13="", "", VLOOKUP(A13, 'ROMANEIO POR ITEM'!#REF!, 5, FALSE)) | F13: =IF(A13="", "", VLOOKUP(A13, 'ROMANEIO POR ITEM'!#REF!, 6, FALSE))
... A1000: =IFERROR(_xlfn.SINGLE(INDEX('ROMANEIO POR ITEM'!#REF!, SMALL(IF(_xlfn.SINGLE('ROMANEIO POR ITEM'!#REF!)<>0,_xlfn.SINGLE( ROW('ROMANEIO POR ITEM'!#REF!))-ROW('ROMANEIO POR ITEM'!#REF!)+1), ROW(A999)))), "") | B1000: =IF(A1000="", "", VLOOKUP(A1000, 'ROMANEIO POR ITEM'!#REF!, 2, FALSE)) | C1000: =IF(A1000="", "", VLOOKUP(A1000, 'ROMANEIO POR ITEM'!#REF!, 3, FALSE)) | D1000: =IF(A1000="", "", VLOOKUP(A1000, 'ROMANEIO POR ITEM'!#REF!, 4, FALSE)) | E1000: =IF(A1000="", "", VLOOKUP(A1000, 'ROMANEIO POR ITEM'!#REF!, 5, FALSE)) | F1000: =IF(A1000="", "", VLOOKUP(A1000, 'ROMANEIO POR ITEM'!#REF!, 6, FALSE))
